Workbook
Name Slicer_Months__Patient_Admission_Date: #N/A
Name Slicer_Months__Patient_Admission_Date1: #N/A
Name Slicer_Months__Patient_Admission_Date2: #N/A
Name Slicer_Months__Patient_Admission_Date3: #N/A
Name Slicer_Week_Slot: #N/A
Name Slicer_Years__Patient_Admission_Date: #N/A
Name Slicer_Years__Patient_Admission_Date1: #N/A
Name Slicer_Years__Patient_Admission_Date2: #N/A
Name Slicer_Years__Patient_Admission_Date3: #N/A

Sheet Hospital Emergency Room Data
A1: Patient Id | B1: Full Name | C1: Patient Admission Date | D1: Month | E1: Year | F1: Patient Admission Time | G1: Week Name | H1: Patient Gender | I1: Patient Age | J1: Age group | K1: Patient Race | L1: Department Referral | M1: Patient Admission Flag | N1: Patient Satisfaction Score | O1: Patient Wait time | P1: Within time or delay | Q1: Day | R1: Hour | S1: Time slot | T1: Week Slot | U1: Wait Time slot | V1: Monthly Period
A2: 145395406 | B2: H. Glasspool | C2: 45371 | D2: =TEXT(Hospital_Emergency_Room_Data[[#This Row],[Patient Admission Date]],"mmm") -> Mar | E2: =YEAR(Hospital_Emergency_Room_Data[[#This Row],[Patient Admission Date]]) -> 2024 | F2: 0.36597222 | G2: =TEXT(Hospital_Emergency_Room_Data[[#This Row],[Patient Admission Date]],"dddd") -> Wednesday | H2: Male | I2: 69 | J2: 60-69 | K2: White | L2: No Department Assigned | M2: Not Admitted | N2: 10 | O2: 39 | P2: Delay | Q2: 20 | R2: 8 | S2: 6AM - 12PM | T2: Week 3 | U2: Slightly Above(<=45) | V2: {=_xlfn.IFS(Hospital_Emergency_Room_Data[[#This Row],[Day]]<=10,"Start(1-10)",Hospital_Emergency_Room_Data[[#This Row],[Day]]<=20,"Middle(11-20)",Hospital_Emergency_Room_Data[[#This Row],[Day]]>20,"End(21-30)")} -> Middle(11-20)
A3: 316343057 | B3: X. Methuen | C3: 45458 | D3: =TEXT(Hospital_Emergency_Room_Data[[#This Row],[Patient Admission Date]],"mmm") -> Jun | E3: =YEAR(Hospital_Emergency_Room_Data[[#This Row],[Patient Admission Date]]) -> 2024 | F3: 0.47847222 | G3: =TEXT(Hospital_Emergency_Room_Data[[#This Row],[Patient Admission Date]],"dddd") -> Saturday | H3: Male | I3: 4 | J3: 0-5 | K3: Native American/Alaska Native | L3: No Department Assigned | M3: Admitted | O3: 27 | P3: Within Time | Q3: 15 | R3: 11 | S3: 6AM - 12PM | T3: Week 3 | U3: Within Target(<30) | V3: {=_xlfn.IFS(Hospital_Emergency_Room_Data[[#This Row],[Day]]<=10,"Start(1-10)",Hospital_Emergency_Room_Data[[#This Row],[Day]]<=20,"Middle(11-20)",Hospital_Emergency_Room_Data[[#This Row],[Day]]>20,"End(21-30)")} -> Middle(11-20)
A4: 897463852 | B4: P. Schubuser | C4: 45463 | D4: =TEXT(Hospital_Emergency_Room_Data[[#This Row],[Patient Admission Date]],"mmm") -> Jun | E4: =YEAR(Hospital_Emergency_Room_Data[[#This Row],[Patient Admission Date]]) -> 2024 | F4: 0.38402778 | G4: =TEXT(Hospital_Emergency_Room_Data[[#This Row],[Patient Admission Date]],"dddd") -> Thursday | H4: Female | I4: 56 | J4: 45-59 | K4: African American | L4: General Practice | M4: Admitted | N4: 9 | O4: 55 | P4: Delay | Q4: 20 | R4: 9 | S4: 6AM - 12PM | T4: Week 3 | U4: Much higher(>45) | V4: {=_xlfn.IFS(Hospital_Emergency_Room_Data[[#This Row],[Day]]<=10,"Start(1-10)",Hospital_Emergency_Room_Data[[#This Row],[Day]]<=20,"Middle(11-20)",Hospital_Emergency_Room_Data[[#This Row],[Day]]>20,"End(21-30)")} -> Middle(11-20)
A5: 358319711 | B5: U. Titcombe | C5: 45326 | D5: =TEXT(Hospital_Emergency_Room_Data[[#This Row],[Patient Admission Date]],"mmm") -> Feb | E5: =YEAR(Hospital_Emergency_Room_Data[[#This Row],[Patient Admission Date]]) -> 2024 | F5: 0.94027778 | G5: =TEXT(Hospital_Emergency_Room_Data[[#This Row],[Patient Admission Date]],"dddd") -> Sunday | H5: Female | I5: 24 | J5: 15-29 | K5: Native American/Alaska Native | L5: General Practice | M5: Admitted | N5: 8 | O5: 31 | P5: Delay | Q5: 4 | R5: 22 | S5: 6PM - 12AM | T5: Week 1 | U5: Slightly Above(<=45) | V5: {=_xlfn.IFS(Hospital_Emergency_Room_Data[[#This Row],[Day]]<=10,"Start(1-10)",Hospital_Emergency_Room_Data[[#This Row],[Day]]<=20,"Middle(11-20)",Hospital_Emergency_Room_Data[[#This Row],[Day]]>20,"End(21-30)")} -> Start(1-10)
A6: 289260537 | B6: Y. Gionettitti | C6: 45539 | D6: =TEXT(Hospital_Emergency_Room_Data[[#This Row],[Patient Admission Date]],"mmm") -> Sep | E6: =YEAR(Hospital_Emergency_Room_Data[[#This Row],[Patient Admission Date]]) -> 2024 | F6: 0.74166667 | G6: =TEXT(Hospital_Emergency_Room_Data[[#This Row],[Patient Admission Date]],"dddd") -> Wednesday | H6: Male | I6: 5 | J6: 5-14 | K6: African American | L6: Orthopedics | M6: Not Admitted | O6: 10 | P6: Within Time | Q6: 4 | R6: 17 | S6: 12PM - 6PM | T6: Week 1 | U6: Within Target(<30) | V6: {=_xlfn.IFS(Hospital_Emergency_Room_Data[[#This Row],[Day]]<=10,"Start(1-10)",Hospital_Emergency_Room_Data[[#This Row],[Day]]<=20,"Middle(11-20)",Hospital_Emergency_Room_Data[[#This Row],[Day]]>20,"End(21-30)")} -> Start(1-10)
A7: 255512877 | B7: H. Buff | C7: 45036 | D7: =TEXT(Hospital_Emergency_Room_Data[[#This Row],[Patient Admission Date]],"mmm") -> Apr | E7: =YEAR(Hospital_Emergency_Room_Data[[#This Row],[Patient Admission Date]]) -> 2023 | F7: 0.0090277778 | G7: =TEXT(Hospital_Emergency_Room_Data[[#This Row],[Patient Admission Date]],"dddd") -> Thursday | H7: Male | I7: 58 | J7: 45-59 | K7: Asian | L7: No Department Assigned | M7: Not Admitted | O7: 59 | P7: Delay | Q7: 20 | R7: 0 | S7: 12AM - 6AM | T7: Week 3 | U7: Much higher(>45) | V7: {=_xlfn.IFS(Hospital_Emergency_Room_Data[[#This Row],[Day]]<=10,"Start(1-10)",Hospital_Emergency_Room_Data[[#This Row],[Day]]<=20,"Middle(11-20)",Hospital_Emergency_Room_Data[[#This Row],[Day]]>20,"End(21-30)")} -> Middle(11-20)
A8: 465970990 | B8: F. Perrat | C8: 45161 | D8: =TEXT(Hospital_Emergency_Room_Data[[#This Row],[Patient Admission Date]],"mmm") -> Aug | E8: =YEAR(Hospital_Emergency_Room_Data[[#This Row],[Patient Admission Date]]) -> 2023 | F8: 0.35138889 | G8: =TEXT(Hospital_Emergency_Room_Data[[#This Row],[Patient Admission Date]],"dddd") -> Wednesday | H8: Female | I8: 68 | J8: 60-69 | K8: White | L8: No Department Assigned | M8: Admitted | O8: 43 | P8: Delay | Q8: 23 | R8: 8 | S8: 6AM - 12PM | T8: Week 4 | U8: Slightly Above(<=45) | V8: {=_xlfn.IFS(Hospital_Emergency_Room_Data[[#This Row],[Day]]<=10,"Start(1-10)",Hospital_Emergency_Room_Data[[#This Row],[Day]]<=20,"Middle(11-20)",Hospital_Emergency_Room_Data[[#This Row],[Day]]>20,"End(21-30)")} -> End(21-30)
A9: 157317520 | B9: K. Gwillim | C9: 45136 | D9: =TEXT(Hospital_Emergency_Room_Data[[#This Row],[Patient Admission Date]],"mmm") -> Jul | E9: =YEAR(Hospital_Emergency_Room_Data[[#This Row],[Patient Admission Date]]) -> 2023 | F9: 0.70625 | G9: =TEXT(Hospital_Emergency_Room_Data[[#This Row],[Patient Admission Date]],"dddd") -> Saturday | H9: Female | I9: 47 | J9: 45-59 | K9: Two or More Races | L9: No Department Assigned | M9: Admitted | O9: 23 | P9: Within Time | Q9: 29 | R9: 16 | S9: 12PM - 6PM | T9: Week 4 | U9: Within Target(<30) | V9: {=_xlfn.IFS(Hospital_Emergency_Room_Data[[#This Row],[Day]]<=10,"Start(1-10)",Hospital_Emergency_Room_Data[[#This Row],[Day]]<=20,"Middle(11-20)",Hospital_Emergency_Room_Data[[#This Row],[Day]]>20,"End(21-30)")} -> End(21-30)
A10: 432345614 | B10: E. Dewhirst | C10: 45341 | D10: =TEXT(Hospital_Emergency_Room_Data[[#This Row],[Patient Admission Date]],"mmm") -> Feb | E10: =YEAR(Hospital_Emergency_Room_Data[[#This Row],[Patient Admission Date]]) -> 2024 | F10: 0.2875 | G10: =TEXT(Hospital_Emergency_Room_Data[[#This Row],[Patient Admission Date]],"dddd") -> Monday | H10: Female | I10: 79 | J10: 70-79 | K10: White | L10: No Department Assigned | M10: Not Admitted | N10: 1 | O10: 42 | P10: Delay | Q10: 19 | R10: 6 | S10: 6AM - 12PM | T10: Week 3 | U10: Slightly Above(<=45) | V10: {=_xlfn.IFS(Hospital_Emergency_Room_Data[[#This Row],[Day]]<=10,"Start(1-10)",Hospital_Emergency_Room_Data[[#This Row],[Day]]<=20,"Middle(11-20)",Hospital_Emergency_Room_Data[[#This Row],[Day]]>20,"End(21-30)")} -> Middle(11-20)
A11: 609178678 | B11: M. Crebo | C11: 45576 | D11: =TEXT(Hospital_Emergency_Room_Data[[#This Row],[Patient Admission Date]],"mmm") -> Oct | E11: =YEAR(Hospital_Emergency_Room_Data[[#This Row],[Patient Admission Date]]) -> 2024 | F11: 0.22569444 | G11: =TEXT(Hospital_Emergency_Room_Data[[#This Row],[Patient Admission Date]],"dddd") -> Friday | H11: Male | I11: 62 | J11: 60-69 | K11: African American | L11: No Department Assigned | M11: Not Admitted | O11: 51 | P11: Delay | Q11: 11 | R11: 5 | S11: 12AM - 6AM | T11: Week 2 | U11: Much higher(>45) | V11: {=_xlfn.IFS(Hospital_Emergency_Room_Data[[#This Row],[Day]]<=10,"Start(1-10)",Hospital_Emergency_Room_Data[[#This Row],[Day]]<=20,"Middle(11-20)",Hospital_Emergency_Room_Data[[#This Row],[Day]]>20,"End(21-30)")} -> Middle(11-20)
A12: 497146812 | B12: Q. Churchard | C12: 45499 | D12: =TEXT(Hospital_Emergency_Room_Data[[#This Row],[Patient Admission Date]],"mmm") -> Jul | E12: =YEAR(Hospital_Emergency_Room_Data[[#This Row],[Patient Admission Date]]) -> 2024 | F12: 0.072916667 | G12: =TEXT(Hospital_Emergency_Room_Data[[#This Row],[Patient Admission Date]],"dddd") -> Friday | H12: Female | I12: 73 | J12: 70-79 | K12: White | L12: Gastroenterology | M12: Admitted | O12: 34 | P12: Delay | Q12: 26 | R12: 1 | S12: 12AM - 6AM | T12: Week 4 | U12: Slightly Above(<=45) | V12: {=_xlfn.IFS(Hospital_Emergency_Room_Data[[#This Row],[Day]]<=10,"Start(1-10)",Hospital_Emergency_Room_Data[[#This Row],[Day]]<=20,"Middle(11-20)",Hospital_Emergency_Room_Data[[#This Row],[Day]]>20,"End(21-30)")} -> End(21-30)
A13: 393389502 | B13: N. Corpes | C13: 45361 | D13: =TEXT(Hospital_Emergency_Room_Data[[#This Row],[Patient Admission Date]],"mmm") -> Mar | E13: =YEAR(Hospital_Emergency_Room_Data[[#This Row],[Patient Admission Date]]) -> 2024 | F13: 0.91805556 | G13: =TEXT(Hospital_Emergency_Room_Data[[#This Row],[Patient Admission Date]],"dddd") -> Sunday | H13: Female | I13: 16 | J13: 15-29 | K13: White | L13: Orthopedics | M13: Not Admitted | O13: 39 | P13: Delay | Q13: 10 | R13: 22 | S13: 6PM - 12AM | T13: Week 2 | U13: Slightly Above(<=45) | V13: {=_xlfn.IFS(Hospital_Emergency_Room_Data[[#This Row],[Day]]<=10,"Start(1-10)",Hospital_Emergency_Room_Data[[#This Row],[Day]]<=20,"Middle(11-20)",Hospital_Emergency_Room_Data[[#This Row],[Day]]>20,"End(21-30)")} -> Start(1-10)
A14: 288056370 | B14: R. Brixey | C14: 45242 | D14: =TEXT(Hospital_Emergency_Room_Data[[#This Row],[Patient Admission Date]],"mmm") -> Nov | E14: =YEAR(Hospital_Emergency_Room_Data[[#This Row],[Patient Admission Date]]) -> 2023 | F14: 0.66666667 | G14: =TEXT(Hospital_Emergency_Room_Data[[#This Row],[Patient Admission Date]],"dddd") -> Sunday | H14: Female | I14: 16 | J14: 15-29 | K14: Native American/Alaska Native | L14: General Practice | M14: Admitted | O14: 53 | P14: Delay | Q14: 12 | R14: 16 | S14: 12PM - 6PM | T14: Week 2 | U14: Much higher(>45) | V14: {=_xlfn.IFS(Hospital_Emergency_Room_Data[[#This Row],[Day]]<=10,"Start(1-10)",Hospital_Emergency_Room_Data[[#This Row],[Day]]<=20,"Middle(11-20)",Hospital_Emergency_Room_Data[[#This Row],[Day]]>20,"End(21-30)")} -> Middle(11-20)
A15: 784549931 | B15: M. Goudie | C15: 45102 | D15: =TEXT(Hospital_Emergency_Room_Data[[#This Row],[Patient Admission Date]],"mmm") -> Jun | E15: =YEAR(Hospital_Emergency_Room_Data[[#This Row],[Patient Admission Date]]) -> 2023 | F15: 0.40277778 | G15: =TEXT(Hospital_Emergency_Room_Data[[#This Row],[Patient Admission Date]],"dddd") -> Sunday | H15: Male | I15: 46 | J15: 45-59 | K15: Pacific Islander | L15: No Department Assigned | M15: Not Admitted | O15: 45 | P15: Delay | Q15: 25 | R15: 9 | S15: 6AM - 12PM | T15: Week 4 | U15: Slightly Above(<=45) | V15: {=_xlfn.IFS(Hospital_Emergency_Room_Data[[#This Row],[Day]]<=10,"Start(1-10)",Hospital_Emergency_Room_Data[[#This Row],[Day]]<=20,"Middle(11-20)",Hospital_Emergency_Room_Data[[#This Row],[Day]]>20,"End(21-30)")} -> End(21-30)
A16: 662216522 | B16: G. Stanlack | C16: 45050 | D16: =TEXT(Hospital_Emergency_Room_Data[[#This Row],[Patient Admission Date]],"mmm") -> May | E16: =YEAR(Hospital_Emergency_Room_Data[[#This Row],[Patient Admission Date]]) -> 2023 | F16: 0.55277778 | G16: =TEXT(Hospital_Emergency_Room_Data[[#This Row],[Patient Admission Date]],"dddd") -> Thursday | H16: Male | I16: 69 | J16: 60-69 | K16: White | L16: No Department Assigned | M16: Admitted | O16: 49 | P16: Delay | Q16: 4 | R16: 13 | S16: 12PM - 6PM | T16: Week 1 | U16: Much higher(>45) | V16: {=_xlfn.IFS(Hospital_Emergency_Room_Data[[#This Row],[Day]]<=10,"Start(1-10)",Hospital_Emergency_Room_Data[[#This Row],[Day]]<=20,"Middle(11-20)",Hospital_Emergency_Room_Data[[#This Row],[Day]]>20,"End(21-30)")} -> Start(1-10)
A17: 628731801 | B17: C. McMurty | C17: 45188 | D17: =TEXT(Hospital_Emergency_Room_Data[[#This Row],[Patient Admission Date]],"mmm") -> Sep | E17: =YEAR(Hospital_Emergency_Room_Data[[#This Row],[Patient Admission Date]]) -> 2023 | F17: 0.078472222 | G17: =TEXT(Hospital_Emergency_Room_Data[[#This Row],[Patient Admission Date]],"dddd") -> Tuesday | H17: Male | I17: 37 | J17: 30-45 | K17: Declined to Identify | L17: No Department Assigned | M17: Admitted | O17: 57 | P17: Delay | Q17: 19 | R17: 1 | S17: 12AM - 6AM | T17: Week 3 | U17: Much higher(>45) | V17: {=_xlfn.IFS(Hospital_Emergency_Room_Data[[#This Row],[Day]]<=10,"Start(1-10)",Hospital_Emergency_Room_Data[[#This Row],[Day]]<=20,"Middle(11-20)",Hospital_Emergency_Room_Data[[#This Row],[Day]]>20,"End(21-30)")} -> Middle(11-20)
A18: 370192271 | B18: I. Scothorn | C18: 45437 | D18: =TEXT(Hospital_Emergency_Room_Data[[#This Row],[Patient Admission Date]],"mmm") -> May | E18: =YEAR(Hospital_Emergency_Room_Data[[#This Row],[Patient Admission Date]]) -> 2024 | F18: 0.92430556 | G18: =TEXT(Hospital_Emergency_Room_Data[[#This Row],[Patient Admission Date]],"dddd") -> Saturday | H18: Female | I18: 50 | J18: 45-59 | K18: Asian | L18: General Practice | M18: Not Admitted | O18: 35 | P18: Delay | Q18: 25 | R18: 22 | S18: 6PM - 12AM | T18: Week 4 | U18: Slightly Above(<=45) | V18: {=_xlfn.IFS(Hospital_Emergency_Room_Data[[#This Row],[Day]]<=10,"Start(1-10)",Hospital_Emergency_Room_Data[[#This Row],[Day]]<=20,"Middle(11-20)",Hospital_Emergency_Room_Data[[#This Row],[Day]]>20,"End(21-30)")} -> End(21-30)
A19: 458988860 | B19: J. Helgass | C19: 45102 | D19: =TEXT(Hospital_Emergency_Room_Data[[#This Row],[Patient Admission Date]],"mmm") -> Jun | E19: =YEAR(Hospital_Emergency_Room_Data[[#This Row],[Patient Admission Date]]) -> 2023 | F19: 0.79097222 | G19: =TEXT(Hospital_Emergency_Room_Data[[#This Row],[Patient Admission Date]],"dddd") -> Sunday | H19: Male | I19: 37 | J19: 30-45 | K19: Declined to Identify | L19: No Department Assigned | M19: Not Admitted | O19: 55 | P19: Delay | Q19: 25 | R19: 18 | S19: 6PM - 12AM | T19: Week 4 | U19: Much higher(>45) | V19: {=_xlfn.IFS(Hospital_Emergency_Room_Data[[#This Row],[Day]]<=10,"Start(1-10)",Hospital_Emergency_Room_Data[[#This Row],[Day]]<=20,"Middle(11-20)",Hospital_Emergency_Room_Data[[#This Row],[Day]]>20,"End(21-30)")} -> End(21-30)
A20: 728312493 | B20: W. Chittock | C20: 45173 | D20: =TEXT(Hospital_Emergency_Room_Data[[#This Row],[Patient Admission Date]],"mmm") -> Sep | E20: =YEAR(Hospital_Emergency_Room_Data[[#This Row],[Patient Admission Date]]) -> 2023 | F20: 0.67708333 | G20: =TEXT(Hospital_Emergency_Room_Data[[#This Row],[Patient Admission Date]],"dddd") -> Monday | H20: Female | I20: 70 | J20: 70-79 | K20: Asian | L20: Physiotherapy | M20: Admitted | O20: 50 | P20: Delay | Q20: 4 | R20: 16 | S20: 12PM - 6PM | T20: Week 1 | U20: Much higher(>45) | V20: {=_xlfn.IFS(Hospital_Emergency_Room_Data[[#This Row],[Day]]<=10,"Start(1-10)",Hospital_Emergency_Room_Data[[#This Row],[Day]]<=20,"Middle(11-20)",Hospital_Emergency_Room_Data[[#This Row],[Day]]>20,"End(21-30)")} -> Start(1-10)
A21: 823345523 | B21: F. Prendergast | C21: 45246 | D21: =TEXT(Hospital_Emergency_Room_Data[[#This Row],[Patient Admission Date]],"mmm") -> Nov | E21: =YEAR(Hospital_Emergency_Room_Data[[#This Row],[Patient Admission Date]]) -> 2023 | F21: 0.99027778 | G21: =TEXT(Hospital_Emergency_Room_Data[[#This Row],[Patient Admission Date]],"dddd") -> Thursday | H21: Male | I21: 55 | J21: 45-59 | K21: Asian | L21: No Department Assigned | M21: Admitted | N21: 2 | O21: 40 | P21: Delay | Q21: 16 | R21: 23 | S21: 6PM - 12AM | T21: Week 3 | U21: Slightly Above(<=45) | V21: {=_xlfn.IFS(Hospital_Emergency_Room_Data[[#This Row],[Day]]<=10,"Start(1-10)",Hospital_Emergency_Room_Data[[#This Row],[Day]]<=20,"Middle(11-20)",Hospital_Emergency_Room_Data[[#This Row],[Day]]>20,"End(21-30)")} -> Middle(11-20)
A22: 621707472 | B22: T. Bissiker | C22: 45107 | D22: =TEXT(Hospital_Emergency_Room_Data[[#This Row],[Patient Admission Date]],"mmm") -> Jun | E22: =YEAR(Hospital_Emergency_Room_Data[[#This Row],[Patient Admission Date]]) -> 2023 | F22: 0.22361111 | G22: =TEXT(Hospital_Emergency_Room_Data[[#This Row],[Patient Admission Date]],"dddd") -> Friday | H22: Female | I22: 63 | J22: 60-69 | K22: Native American/Alaska Native | L22: No Department Assigned | M22: Admitted | O22: 25 | P22: Within Time | Q22: 30 | R22: 5 | S22: 12AM - 6AM | T22: Week 4 | U22: Within Target(<30) | V22: {=_xlfn.IFS(Hospital_Emergency_Room_Data[[#This Row],[Day]]<=10,"Start(1-10)",Hospital_Emergency_Room_Data[[#This Row],[Day]]<=20,"Middle(11-20)",Hospital_Emergency_Room_Data[[#This Row],[Day]]>20,"End(21-30)")} -> End(21-30)
A23: 344367156 | B23: M. Mandell | C23: 45068 | D23: =TEXT(Hospital_Emergency_Room_Data[[#This Row],[Patient Admission Date]],"mmm") -> May | E23: =YEAR(Hospital_Emergency_Room_Data[[#This Row],[Patient Admission Date]]) -> 2023 | F23: 0.7 | G23: =TEXT(Hospital_Emergency_Room_Data[[#This Row],[Patient Admission Date]],"dddd") -> Monday | H23: Female | I23: 44 | J23: 30-45 | K23: Asian | L23: No Department Assigned | M23: Not Admitted | N23: 2 | O23: 51 | P23: Delay | Q23: 22 | R23: 16 | S23: 12PM - 6PM | T23: Week 4 | U23: Much higher(>45) | V23: {=_xlfn.IFS(Hospital_Emergency_Room_Data[[#This Row],[Day]]<=10,"Start(1-10)",Hospital_Emergency_Room_Data[[#This Row],[Day]]<=20,"Middle(11-20)",Hospital_Emergency_Room_Data[[#This Row],[Day]]>20,"End(21-30)")} -> End(21-30)
A24: 455213671 | B24: D. Coste | C24: 45247 | D24: =TEXT(Hospital_Emergency_Room_Data[[#This Row],[Patient Admission Date]],"mmm") -> Nov | E24: =YEAR(Hospital_Emergency_Room_Data[[#This Row],[Patient Admission Date]]) -> 2023 | F24: 0.30833333 | G24: =TEXT(Hospital_Emergency_Room_Data[[#This Row],[Patient Admission Date]],"dddd") -> Friday | H24: Female | I24: 11 | J24: 5-14 | K24: Declined to Identify | L24: No Department Assigned | M24: Not Admitted | N24: 4 | O24: 30 | P24: Delay | Q24: 17 | R24: 7 | S24: 6AM - 12PM | T24: Week 3 | U24: Within Target(<30) | V24: {=_xlfn.IFS(Hospital_Emergency_Room_Data[[#This Row],[Day]]<=10,"Start(1-10)",Hospital_Emergency_Room_Data[[#This Row],[Day]]<=20,"Middle(11-20)",Hospital_Emergency_Room_Data[[#This Row],[Day]]>20,"End(21-30)")} -> Middle(11-20)
A25: 259100339 | B25: Q. Dodridge | C25: 45317 | D25: =TEXT(Hospital_Emergency_Room_Data[[#This Row],[Patient Admission Date]],"mmm") -> Jan | E25: =YEAR(Hospital_Emergency_Room_Data[[#This Row],[Patient Admission Date]]) -> 2024 | F25: 0.24861111 | G25: =TEXT(Hospital_Emergency_Room_Data[[#This Row],[Patient Admission Date]],"dddd") -> Friday | H25: Male | I25: 8 | J25: 5-14 | K25: Asian | L25: General Practice | M25: Not Admitted | O25: 16 | P25: Within Time | Q25: 26 | R25: 5 | S25: 12AM - 6AM | T25: Week 4 | U25: Within Target(<30) | V25: {=_xlfn.IFS(Hospital_Emergency_Room_Data[[#This Row],[Day]]<=10,"Start(1-10)",Hospital_Emergency_Room_Data[[#This Row],[Day]]<=20,"Middle(11-20)",Hospital_Emergency_Room_Data[[#This Row],[Day]]>20,"End(21-30)")} -> End(21-30)
A26: 720542625 | B26: C. Pavie | C26: 45070 | D26: =TEXT(Hospital_Emergency_Room_Data[[#This Row],[Patient Admission Date]],"mmm") -> May | E26: =YEAR(Hospital_Emergency_Room_Data[[#This Row],[Patient Admission Date]]) -> 2023 | F26: 0.6125 | G26: =TEXT(Hospital_Emergency_Room_Data[[#This Row],[Patient Admission Date]],"dddd") -> Wednesday | H26: Female | I26: 4 | J26: 0-5 | K26: Native American/Alaska Native | L26: No Department Assigned | M26: Admitted | O26: 23 | P26: Within Time | Q26: 24 | R26: 14 | S26: 12PM - 6PM | T26: Week 4 | U26: Within Target(<30) | V26: {=_xlfn.IFS(Hospital_Emergency_Room_Data[[#This Row],[Day]]<=10,"Start(1-10)",Hospital_Emergency_Room_Data[[#This Row],[Day]]<=20,"Middle(11-20)",Hospital_Emergency_Room_Data[[#This Row],[Day]]>20,"End(21-30)")} -> End(21-30)
A27: 661927059 | B27: Z. Sleightholm | C27: 45028 | D27: =TEXT(Hospital_Emergency_Room_Data[[#This Row],[Patient Admission Date]],"mmm") -> Apr | E27: =YEAR(Hospital_Emergency_Room_Data[[#This Row],[Patient Admission Date]]) -> 2023 | F27: 0.87638889 | G27: =TEXT(Hospital_Emergency_Room_Data[[#This Row],[Patient Admission Date]],"dddd") -> Wednesday | H27: Male | I27: 42 | J27: 30-45 | K27: African American | L27: No Department Assigned | M27: Not Admitted | N27: 0 | O27: 51 | P27: Delay | Q27: 12 | R27: 21 | S27: 6PM - 12AM | T27: Week 2 | U27: Much higher(>45) | V27: {=_xlfn.IFS(Hospital_Emergency_Room_Data[[#This Row],[Day]]<=10,"Start(1-10)",Hospital_Emergency_Room_Data[[#This Row],[Day]]<=20,"Middle(11-20)",Hospital_Emergency_Room_Data[[#This Row],[Day]]>20,"End(21-30)")} -> Middle(11-20)
A28: 598533927 | B28: S. Noads | C28: 45539 | D28: =TEXT(Hospital_Emergency_Room_Data[[#This Row],[Patient Admission Date]],"mmm") -> Sep | E28: =YEAR(Hospital_Emergency_Room_Data[[#This Row],[Patient Admission Date]]) -> 2024 | F28: 0.10416667 | G28: =TEXT(Hospital_Emergency_Room_Data[[#This Row],[Patient Admission Date]],"dddd") -> Wednesday | H28: Female | I28: 68 | J28: 60-69 | K28: African American | L28: No Department Assigned | M28: Not Admitted | O28: 58 | P28: Delay | Q28: 4 | R28: 2 | S28: 12AM - 6AM | T28: Week 1 | U28: Much higher(>45) | V28: {=_xlfn.IFS(Hospital_Emergency_Room_Data[[#This Row],[Day]]<=10,"Start(1-10)",Hospital_Emergency_Room_Data[[#This Row],[Day]]<=20,"Middle(11-20)",Hospital_Emergency_Room_Data[[#This Row],[Day]]>20,"End(21-30)")} -> Start(1-10)
A29: 715745338 | B29: J. Filkin | C29: 45276 | D29: =TEXT(Hospital_Emergency_Room_Data[[#This Row],[Patient Admission Date]],"mmm") -> Dec | E29: =YEAR(Hospital_Emergency_Room_Data[[#This Row],[Patient Admission Date]]) -> 2023 | F29: 0.54305556 | G29: =TEXT(Hospital_Emergency_Room_Data[[#This Row],[Patient Admission Date]],"dddd") -> Saturday | H29: Male | I29: 22 | J29: 15-29 | K29: Pacific Islander | L29: General Practice | M29: Not Admitted | O29: 25 | P29: Within Time | Q29: 16 | R29: 13 | S29: 12PM - 6PM | T29: Week 3 | U29: Within Target(<30) | V29: {=_xlfn.IFS(Hospital_Emergency_Room_Data[[#This Row],[Day]]<=10,"Start(1-10)",Hospital_Emergency_Room_Data[[#This Row],[Day]]<=20,"Middle(11-20)",Hospital_Emergency_Room_Data[[#This Row],[Day]]>20,"End(21-30)")} -> Middle(11-20)
A30: 669742146 | B30: C. Bilby | C30: 45362 | D30: =TEXT(Hospital_Emergency_Room_Data[[#This Row],[Patient Admission Date]],"mmm") -> Mar | E30: =YEAR(Hospital_Emergency_Room_Data[[#This Row],[Patient Admission Date]]) -> 2024 | F30: 0.7125 | G30: =TEXT(Hospital_Emergency_Room_Data[[#This Row],[Patient Admission Date]],"dddd") -> Monday | H30: Female | I30: 58 | J30: 45-59 | K30: Declined to Identify | L30: Orthopedics | M30: Not Admitted | O30: 55 | P30: Delay | Q30: 11 | R30: 17 | S30: 12PM - 6PM | T30: Week 2 | U30: Much higher(>45) | V30: {=_xlfn.IFS(Hospital_Emergency_Room_Data[[#This Row],[Day]]<=10,"Start(1-10)",Hospital_Emergency_Room_Data[[#This Row],[Day]]<=20,"Middle(11-20)",Hospital_Emergency_Room_Data[[#This Row],[Day]]>20,"End(21-30)")} -> Middle(11-20)
A31: 693382084 | B31: H. Kehoe | C31: 45480 | D31: =TEXT(Hospital_Emergency_Room_Data[[#This Row],[Patient Admission Date]],"mmm") -> Jul | E31: =YEAR(Hospital_Emergency_Room_Data[[#This Row],[Patient Admission Date]]) -> 2024 | F31: 0.62361111 | G31: =TEXT(Hospital_Emergency_Room_Data[[#This Row],[Patient Admission Date]],"dddd") -> Sunday | H31: Female | I31: 72 | J31: 70-79 | K31: African American | L31: No Department Assigned | M31: Admitted | O31: 37 | P31: Delay | Q31: 7 | R31: 14 | S31: 12PM - 6PM | T31: Week 1 | U31: Slightly Above(<=45) | V31: {=_xlfn.IFS(Hospital_Emergency_Room_Data[[#This Row],[Day]]<=10,"Start(1-10)",Hospital_Emergency_Room_Data[[#This Row],[Day]]<=20,"Middle(11-20)",Hospital_Emergency_Room_Data[[#This Row],[Day]]>20,"End(21-30)")} -> Start(1-10)
A32: 548939953 | B32: S. O'Neill | C32: 45384 | D32: =TEXT(Hospital_Emergency_Room_Data[[#This Row],[Patient Admission Date]],"mmm") -> Apr | E32: =YEAR(Hospital_Emergency_Room_Data[[#This Row],[Patient Admission Date]]) -> 2024 | F32: 0.55486111 | G32: =TEXT(Hospital_Emergency_Room_Data[[#This Row],[Patient Admission Date]],"dddd") -> Tuesday | H32: Female | I32: 73 | J32: 70-79 | K32: Two or More Races | L32: Neurology | M32: Not Admitted | O32: 46 | P32: Delay | Q32: 2 | R32: 13 | S32: 12PM - 6PM | T32: Week 1 | U32: Much higher(>45) | V32: {=_xlfn.IFS(Hospital_Emergency_Room_Data[[#This Row],[Day]]<=10,"Start(1-10)",Hospital_Emergency_Room_Data[[#This Row],[Day]]<=20,"Middle(11-20)",Hospital_Emergency_Room_Data[[#This Row],[Day]]>20,"End(21-30)")} -> Start(1-10)
A33: 334764005 | B33: J. Sibbit | C33: 45107 | D33: =TEXT(Hospital_Emergency_Room_Data[[#This Row],[Patient Admission Date]],"mmm") -> Jun | E33: =YEAR(Hospital_Emergency_Room_Data[[#This Row],[Patient Admission Date]]) -> 2023 | F33: 0.94305556 | G33: =TEXT(Hospital_Emergency_Room_Data[[#This Row],[Patient Admission Date]],"dddd") -> Friday | H33: Male | I33: 35 | J33: 30-45 | K33: White | L33: Orthopedics | M33: Admitted | O33: 40 | P33: Delay | Q33: 30 | R33: 22 | S33: 6PM - 12AM | T33: Week 4 | U33: Slightly Above(<=45) | V33: {=_xlfn.IFS(Hospital_Emergency_Room_Data[[#This Row],[Day]]<=10,"Start(1-10)",Hospital_Emergency_Room_Data[[#This Row],[Day]]<=20,"Middle(11-20)",Hospital_Emergency_Room_Data[[#This Row],[Day]]>20,"End(21-30)")} -> End(21-30)
A34: 846667490 | B34: T. Clissett | C34: 45509 | D34: =TEXT(Hospital_Emergency_Room_Data[[#This Row],[Patient Admission Date]],"mmm") -> Aug | E34: =YEAR(Hospital_Emergency_Room_Data[[#This Row],[Patient Admission Date]]) -> 2024 | F34: 0.63680556 | G34: =TEXT(Hospital_Emergency_Room_Data[[#This Row],[Patient Admission Date]],"dddd") -> Monday | H34: Male | I34: 48 | J34: 45-59 | K34: White | L34: No Department Assigned | M34: Not Admitted | O34: 53 | P34: Delay | Q34: 5 | R34: 15 | S34: 12PM - 6PM | T34: Week 1 | U34: Much higher(>45) | V34: {=_xlfn.IFS(Hospital_Emergency_Room_Data[[#This Row],[Day]]<=10,"Start(1-10)",Hospital_Emergency_Room_Data[[#This Row],[Day]]<=20,"Middle(11-20)",Hospital_Emergency_Room_Data[[#This Row],[Day]]>20,"End(21-30)")} -> Start(1-10)
A35: 278496531 | B35: L. Vannacci | C35: 45509 | D35: =TEXT(Hospital_Emergency_Room_Data[[#This Row],[Patient Admission Date]],"mmm") -> Aug | E35: =YEAR(Hospital_Emergency_Room_Data[[#This Row],[Patient Admission Date]]) -> 2024 | F35: 0.064583333 | G35: =TEXT(Hospital_Emergency_Room_Data[[#This Row],[Patient Admission Date]],"dddd") -> Monday | H35: Female | I35: 74 | J35: 70-79 | K35: White | L35: Physiotherapy | M35: Not Admitted | N35: 0 | O35: 20 | P35: Within Time | Q35: 5 | R35: 1 | S35: 12AM - 6AM | T35: Week 1 | U35: Within Target(<30) | V35: {=_xlfn.IFS(Hospital_Emergency_Room_Data[[#This Row],[Day]]<=10,"Start(1-10)",Hospital_Emergency_Room_Data[[#This Row],[Day]]<=20,"Middle(11-20)",Hospital_Emergency_Room_Data[[#This Row],[Day]]>20,"End(21-30)")} -> Start(1-10)
A36: 600623412 | B36: H. Ponting | C36: 45307 | D36: =TEXT(Hospital_Emergency_Room_Data[[#This Row],[Patient Admission Date]],"mmm") -> Jan | E36: =YEAR(Hospital_Emergency_Room_Data[[#This Row],[Patient Admission Date]]) -> 2024 | F36: 0.83680556 | G36: =TEXT(Hospital_Emergency_Room_Data[[#This Row],[Patient Admission Date]],"dddd") -> Tuesday | H36: Male | I36: 14 | J36: 5-14 | K36: Two or More Races | L36: No Department Assigned | M36: Admitted | O36: 52 | P36: Delay | Q36: 16 | R36: 20 | S36: 6PM - 12AM | T36: Week 3 | U36: Much higher(>45) | V36: {=_xlfn.IFS(Hospital_Emergency_Room_Data[[#This Row],[Day]]<=10,"Start(1-10)",Hospital_Emergency_Room_Data[[#This Row],[Day]]<=20,"Middle(11-20)",Hospital_Emergency_Room_Data[[#This Row],[Day]]>20,"End(21-30)")} -> Middle(11-20)
A37: 745629973 | B37: D. Bleacher | C37: 45299 | D37: =TEXT(Hospital_Emergency_Room_Data[[#This Row],[Patient Admission Date]],"mmm") -> Jan | E37: =YEAR(Hospital_Emergency_Room_Data[[#This Row],[Patient Admission Date]]) -> 2024 | F37: 0.99652778 | G37: =TEXT(Hospital_Emergency_Room_Data[[#This Row],[Patient Admission Date]],"dddd") -> Monday | H37: Female | I37: 37 | J37: 30-45 | K37: Declined to Identify | L37: No Department Assigned | M37: Admitted | O37: 49 | P37: Delay | Q37: 8 | R37: 23 | S37: 6PM - 12AM | T37: Week 2 | U37: Much higher(>45) | V37: {=_xlfn.IFS(Hospital_Emergency_Room_Data[[#This Row],[Day]]<=10,"Start(1-10)",Hospital_Emergency_Room_Data[[#This Row],[Day]]<=20,"Middle(11-20)",Hospital_Emergency_Room_Data[[#This Row],[Day]]>20,"End(21-30)")} -> Start(1-10)
A38: 384705840 | B38: B. Drinkeld | C38: 45274 | D38: =TEXT(Hospital_Emergency_Room_Data[[#This Row],[Patient Admission Date]],"mmm") -> Dec | E38: =YEAR(Hospital_Emergency_Room_Data[[#This Row],[Patient Admission Date]]) -> 2023 | F38: 0.89027778 | G38: =TEXT(Hospital_Emergency_Room_Data[[#This Row],[Patient Admission Date]],"dddd") -> Thursday | H38: Male | I38: 25 | J38: 15-29 | K38: African American | L38: No Department Assigned | M38: Not Admitted | O38: 10 | P38: Within Time | Q38: 14 | R38: 21 | S38: 6PM - 12AM | T38: Week 2 | U38: Within Target(<30) | V38: {=_xlfn.IFS(Hospital_Emergency_Room_Data[[#This Row],[Day]]<=10,"Start(1-10)",Hospital_Emergency_Room_Data[[#This Row],[Day]]<=20,"Middle(11-20)",Hospital_Emergency_Room_Data[[#This Row],[Day]]>20,"End(21-30)")} -> Middle(11-20)
A39: 285410221 | B39: N. Aggiss | C39: 45485 | D39: =TEXT(Hospital_Emergency_Room_Data[[#This Row],[Patient Admission Date]],"mmm") -> Jul | E39: =YEAR(Hospital_Emergency_Room_Data[[#This Row],[Patient Admission Date]]) -> 2024 | F39: 0.55 | G39: =TEXT(Hospital_Emergency_Room_Data[[#This Row],[Patient Admission Date]],"dddd") -> Friday | H39: Male | I39: 39 | J39: 30-45 | K39: Two or More Races | L39: Orthopedics | M39: Not Admitted | O39: 52 | P39: Delay | Q39: 12 | R39: 13 | S39: 12PM - 6PM | T39: Week 2 | U39: Much higher(>45) | V39: {=_xlfn.IFS(Hospital_Emergency_Room_Data[[#This Row],[Day]]<=10,"Start(1-10)",Hospital_Emergency_Room_Data[[#This Row],[Day]]<=20,"Middle(11-20)",Hospital_Emergency_Room_Data[[#This Row],[Day]]>20,"End(21-30)")} -> Middle(11-20)
A40: 124733676 | B40: K. Bilofsky | C40: 45444 | D40: =TEXT(Hospital_Emergency_Room_Data[[#This Row],[Patient Admission Date]],"mmm") -> Jun | E40: =YEAR(Hospital_Emergency_Room_Data[[#This Row],[Patient Admission Date]]) -> 2024 | F40: 0.44027778 | G40: =TEXT(Hospital_Emergency_Room_Data[[#This Row],[Patient Admission Date]],"dddd") -> Saturday | H40: Male | I40: 48 | J40: 45-59 | K40: Declined to Identify | L40: No Department Assigned | M40: Not Admitted | O40: 35 | P40: Delay | Q40: 1 | R40: 10 | S40: 6AM - 12PM | T40: Week 1 | U40: Slightly Above(<=45) | V40: {=_xlfn.IFS(Hospital_Emergency_Room_Data[[#This Row],[Day]]<=10,"Start(1-10)",Hospital_Emergency_Room_Data[[#This Row],[Day]]<=20,"Middle(11-20)",Hospital_Emergency_Room_Data[[#This Row],[Day]]>20,"End(21-30)")} -> Start(1-10)
A41: 878550051 | B41: R. Harrington | C41: 45113 | D41: =TEXT(Hospital_Emergency_Room_Data[[#This Row],[Patient Admission Date]],"mmm") -> Jul | E41: =YEAR(Hospital_Emergency_Room_Data[[#This Row],[Patient Admission Date]]) -> 2023 | F41: 0.82430556 | G41: =TEXT(Hospital_Emergency_Room_Data[[#This Row],[Patient Admission Date]],"dddd") -> Thursday | H41: Female | I41: 22 | J41: 15-29 | K41: African American | L41: General Practice | M41: Not Admitted | O41: 16 | P41: Within Time | Q41: 6 | R41: 19 | S41: 6PM - 12AM | T41: Week 1 | U41: Within Target(<30) | V41: {=_xlfn.IFS(Hospital_Emergency_Room_Data[[#This Row],[Day]]<=10,"Start(1-10)",Hospital_Emergency_Room_Data[[#This Row],[Day]]<=20,"Middle(11-20)",Hospital_Emergency_Room_Data[[#This Row],[Day]]>20,"End(21-30)")} -> Start(1-10)
A42: 206254281 | B42: D. Yarrington | C42: 45458 | D42: =TEXT(Hospital_Emergency_Room_Data[[#This Row],[Patient Admission Date]],"mmm") -> Jun | E42: =YEAR(Hospital_Emergency_Room_Data[[#This Row],[Patient Admission Date]]) -> 2024 | F42: 0.56944444 | G42: =TEXT(Hospital_Emergency_Room_Data[[#This Row],[Patient Admission Date]],"dddd") -> Saturday | H42: Female | I42: 72 | J42: 70-79 | K42: Declined to Identify | L42: No Department Assigned | M42: Admitted | N42: 7 | O42: 33 | P42: Delay | Q42: 15 | R42: 13 | S42: 12PM - 6PM | T42: Week 3 | U42: Slightly Above(<=45) | V42: {=_xlfn.IFS(Hospital_Emergency_Room_Data[[#This Row],[Day]]<=10,"Start(1-10)",Hospital_Emergency_Room_Data[[#This Row],[Day]]<=20,"Middle(11-20)",Hospital_Emergency_Room_Data[[#This Row],[Day]]>20,"End(21-30)")} -> Middle(11-20)
A43: 472285842 | B43: N. Gulliman | C43: 45211 | D43: =TEXT(Hospital_Emergency_Room_Data[[#This Row],[Patient Admission Date]],"mmm") -> Oct | E43: =YEAR(Hospital_Emergency_Room_Data[[#This Row],[Patient Admission Date]]) -> 2023 | F43: 0.62708333 | G43: =TEXT(Hospital_Emergency_Room_Data[[#This Row],[Patient Admission Date]],"dddd") -> Thursday | H43: Female | I43: 41 | J43: 30-45 | K43: Pacific Islander | L43: No Department Assigned | M43: Not Admitted | O43: 16 | P43: Within Time | Q43: 12 | R43: 15 | S43: 12PM - 6PM | T43: Week 2 | U43: Within Target(<30) | V43: {=_xlfn.IFS(Hospital_Emergency_Room_Data[[#This Row],[Day]]<=10,"Start(1-10)",Hospital_Emergency_Room_Data[[#This Row],[Day]]<=20,"Middle(11-20)",Hospital_Emergency_Room_Data[[#This Row],[Day]]>20,"End(21-30)")} -> Middle(11-20)
A44: 553278559 | B44: Q. Garnsworthy | C44: 45073 | D44: =TEXT(Hospital_Emergency_Room_Data[[#This Row],[Patient Admission Date]],"mmm") -> May | E44: =YEAR(Hospital_Emergency_Room_Data[[#This Row],[Patient Admission Date]]) -> 2023 | F44: 0.25902778 | G44: =TEXT(Hospital_Emergency_Room_Data[[#This Row],[Patient Admission Date]],"dddd") -> Saturday | H44: Female | I44: 8 | J44: 5-14 | K44: African American | L44: General Practice | M44: Not Admitted | O44: 59 | P44: Delay | Q44: 27 | R44: 6 | S44: 6AM - 12PM | T44: Week 4 | U44: Much higher(>45) | V44: {=_xlfn.IFS(Hospital_Emergency_Room_Data[[#This Row],[Day]]<=10,"Start(1-10)",Hospital_Emergency_Room_Data[[#This Row],[Day]]<=20,"Middle(11-20)",Hospital_Emergency_Room_Data[[#This Row],[Day]]>20,"End(21-30)")} -> End(21-30)
A45: 319839008 | B45: H. Hesbrook | C45: 45374 | D45: =TEXT(Hospital_Emergency_Room_Data[[#This Row],[Patient Admission Date]],"mmm") -> Mar | E45: =YEAR(Hospital_Emergency_Room_Data[[#This Row],[Patient Admission Date]]) -> 2024 | F45: 0.57152778 | G45: =TEXT(Hospital_Emergency_Room_Data[[#This Row],[Patient Admission Date]],"dddd") -> Saturday | H45: Female | I45: 70 | J45: 70-79 | K45: Native American/Alaska Native | L45: No Department Assigned | M45: Admitted | O45: 39 | P45: Delay | Q45: 23 | R45: 13 | S45: 12PM - 6PM | T45: Week 4 | U45: Slightly Above(<=45) | V45: {=_xlfn.IFS(Hospital_Emergency_Room_Data[[#This Row],[Day]]<=10,"Start(1-10)",Hospital_Emergency_Room_Data[[#This Row],[Day]]<=20,"Middle(11-20)",Hospital_Emergency_Room_Data[[#This Row],[Day]]>20,"End(21-30)")} -> End(21-30)
A46: 434165502 | B46: N. Romanet | C46: 45024 | D46: =TEXT(Hospital_Emergency_Room_Data[[#This Row],[Patient Admission Date]],"mmm") -> Apr | E46: =YEAR(Hospital_Emergency_Room_Data[[#This Row],[Patient Admission Date]]) -> 2023 | F46: 0.54097222 | G46: =TEXT(Hospital_Emergency_Room_Data[[#This Row],[Patient Admission Date]],"dddd") -> Saturday | H46: Female | I46: 50 | J46: 45-59 | K46: White | L46: No Department Assigned | M46: Admitted | O46: 37 | P46: Delay | Q46: 8 | R46: 12 | S46: 12PM - 6PM | T46: Week 2 | U46: Slightly Above(<=45) | V46: {=_xlfn.IFS(Hospital_Emergency_Room_Data[[#This Row],[Day]]<=10,"Start(1-10)",Hospital_Emergency_Room_Data[[#This Row],[Day]]<=20,"Middle(11-20)",Hospital_Emergency_Room_Data[[#This Row],[Day]]>20,"End(21-30)")} -> Start(1-10)
A47: 672892190 | B47: K. Rushmare | C47: 45172 | D47: =TEXT(Hospital_Emergency_Room_Data[[#This Row],[Patient Admission Date]],"mmm") -> Sep | E47: =YEAR(Hospital_Emergency_Room_Data[[#This Row],[Patient Admission Date]]) -> 2023 | F47: 0.77708333 | G47: =TEXT(Hospital_Emergency_Room_Data[[#This Row],[Patient Admission Date]],"dddd") -> Sunday | H47: Female | I47: 33 | J47: 30-45 | K47: Declined to Identify | L47: No Department Assigned | M47: Admitted | N47: 3 | O47: 16 | P47: Within Time | Q47: 3 | R47: 18 | S47: 6PM - 12AM | T47: Week 1 | U47: Within Target(<30) | V47: {=_xlfn.IFS(Hospital_Emergency_Room_Data[[#This Row],[Day]]<=10,"Start(1-10)",Hospital_Emergency_Room_Data[[#This Row],[Day]]<=20,"Middle(11-20)",Hospital_Emergency_Room_Data[[#This Row],[Day]]>20,"End(21-30)")} -> Start(1-10)
A48: 135054896 | B48: P. Pow | C48: 45136 | D48: =TEXT(Hospital_Emergency_Room_Data[[#This Row],[Patient Admission Date]],"mmm") -> Jul | E48: =YEAR(Hospital_Emergency_Room_Data[[#This Row],[Patient Admission Date]]) -> 2023 | F48: 0.73402778 | G48: =TEXT(Hospital_Emergency_Room_Data[[#This Row],[Patient Admission Date]],"dddd") -> Saturday | H48: Male | I48: 17 | J48: 15-29 | K48: Two or More Races | L48: No Department Assigned | M48: Not Admitted | O48: 56 | P48: Delay | Q48: 29 | R48: 17 | S48: 12PM - 6PM | T48: Week 4 | U48: Much higher(>45) | V48: {=_xlfn.IFS(Hospital_Emergency_Room_Data[[#This Row],[Day]]<=10,"Start(1-10)",Hospital_Emergency_Room_Data[[#This Row],[Day]]<=20,"Middle(11-20)",Hospital_Emergency_Room_Data[[#This Row],[Day]]>20,"End(21-30)")} -> End(21-30)
A49: 760334176 | B49: Q. Dear | C49: 45514 | D49: =TEXT(Hospital_Emergency_Room_Data[[#This Row],[Patient Admission Date]],"mmm") -> Aug | E49: =YEAR(Hospital_Emergency_Room_Data[[#This Row],[Patient Admission Date]]) -> 2024 | F49: 0.10972222 | G49: =TEXT(Hospital_Emergency_Room_Data[[#This Row],[Patient Admission Date]],"dddd") -> Saturday | H49: Female | I49: 45 | J49: 45-59 | K49: White | L49: Orthopedics | M49: Not Admitted | O49: 57 | P49: Delay | Q49: 10 | R49: 2 | S49: 12AM - 6AM | T49: Week 2 | U49: Much higher(>45) | V49: {=_xlfn.IFS(Hospital_Emergency_Room_Data[[#This Row],[Day]]<=10,"Start(1-10)",Hospital_Emergency_Room_Data[[#This Row],[Day]]<=20,"Middle(11-20)",Hospital_Emergency_Room_Data[[#This Row],[Day]]>20,"End(21-30)")} -> Start(1-10)
A50: 624719493 | B50: X. Leake | C50: 45210 | D50: =TEXT(Hospital_Emergency_Room_Data[[#This Row],[Patient Admission Date]],"mmm") -> Oct | E50: =YEAR(Hospital_Emergency_Room_Data[[#This Row],[Patient Admission Date]]) -> 2023 | F50: 0.080555556 | G50: =TEXT(Hospital_Emergency_Room_Data[[#This Row],[Patient Admission Date]],"dddd") -> Wednesday | H50: Female | I50: 53 | J50: 45-59 | K50: White | L50: No Department Assigned | M50: Not Admitted | O50: 21 | P50: Within Time | Q50: 11 | R50: 1 | S50: 12AM - 6AM | T50: Week 2 | U50: Within Target(<30) | V50: {=_xlfn.IFS(Hospital_Emergency_Room_Data[[#This Row],[Day]]<=10,"Start(1-10)",Hospital_Emergency_Room_Data[[#This Row],[Day]]<=20,"Middle(11-20)",Hospital_Emergency_Room_Data[[#This Row],[Day]]>20,"End(21-30)")} -> Middle(11-20)
A51: 479428894 | B51: Z. Friman | C51: 45034 | D51: =TEXT(Hospital_Emergency_Room_Data[[#This Row],[Patient Admission Date]],"mmm") -> Apr | E51: =YEAR(Hospital_Emergency_Room_Data[[#This Row],[Patient Admission Date]]) -> 2023 | F51: 0.94861111 | G51: =TEXT(Hospital_Emergency_Room_Data[[#This Row],[Patient Admission Date]],"dddd") -> Tuesday | H51: Female | I51: 15 | J51: 15-29 | K51: White | L51: No Department Assigned | M51: Not Admitted | O51: 29 | P51: Within Time | Q51: 18 | R51: 22 | S51: 6PM - 12AM | T51: Week 3 | U51: Within Target(<30) | V51: {=_xlfn.IFS(Hospital_Emergency_Room_Data[[#This Row],[Day]]<=10,"Start(1-10)",Hospital_Emergency_Room_Data[[#This Row],[Day]]<=20,"Middle(11-20)",Hospital_Emergency_Room_Data[[#This Row],[Day]]>20,"End(21-30)")} -> Middle(11-20)
A52: 324754743 | B52: T. Aldridge | C52: 45543 | D52: =TEXT(Hospital_Emergency_Room_Data[[#This Row],[Patient Admission Date]],"mmm") -> Sep | E52: =YEAR(Hospital_Emergency_Room_Data[[#This Row],[Patient Admission Date]]) -> 2024 | F52: 0.43472222 | G52: =TEXT(Hospital_Emergency_Room_Data[[#This Row],[Patient Admission Date]],"dddd") -> Sunday | H52: Male | I52: 48 | J52: 45-59 | K52: Pacific Islander | L52: No Department Assigned | M52: Not Admitted | O52: 13 | P52: Within Time | Q52: 8 | R52: 10 | S52: 6AM - 12PM | T52: Week 2 | U52: Within Target(<30) | V52: {=_xlfn.IFS(Hospital_Emergency_Room_Data[[#This Row],[Day]]<=10,"Start(1-10)",Hospital_Emergency_Room_Data[[#This Row],[Day]]<=20,"Middle(11-20)",Hospital_Emergency_Room_Data[[#This Row],[Day]]>20,"End(21-30)")} -> Start(1-10)
A53: 207154815 | B53: O. Brattan | C53: 45438 | D53: =TEXT(Hospital_Emergency_Room_Data[[#This Row],[Patient Admission Date]],"mmm") -> May | E53: =YEAR(Hospital_Emergency_Room_Data[[#This Row],[Patient Admission Date]]) -> 2024 | F53: 0.28541667 | G53: =TEXT(Hospital_Emergency_Room_Data[[#This Row],[Patient Admission Date]],"dddd") -> Sunday | H53: Female | I53: 20 | J53: 15-29 | K53: Asian | L53: No Department Assigned | M53: Admitted | O53: 53 | P53: Delay | Q53: 26 | R53: 6 | S53: 6AM - 12PM | T53: Week 4 | U53: Much higher(>45) | V53: {=_xlfn.IFS(Hospital_Emergency_Room_Data[[#This Row],[Day]]<=10,"Start(1-10)",Hospital_Emergency_Room_Data[[#This Row],[Day]]<=20,"Middle(11-20)",Hospital_Emergency_Room_Data[[#This Row],[Day]]>20,"End(21-30)")} -> End(21-30)
A54: 407451728 | B54: L. Bourcq | C54: 45427 | D54: =TEXT(Hospital_Emergency_Room_Data[[#This Row],[Patient Admission Date]],"mmm") -> May | E54: =YEAR(Hospital_Emergency_Room_Data[[#This Row],[Patient Admission Date]]) -> 2024 | F54: 0.88194444 | G54: =TEXT(Hospital_Emergency_Room_Data[[#This Row],[Patient Admission Date]],"dddd") -> Wednesday | H54: Male | I54: 45 | J54: 45-59 | K54: Asian | L54: No Department Assigned | M54: Not Admitted | O54: 37 | P54: Delay | Q54: 15 | R54: 21 | S54: 6PM - 12AM | T54: Week 3 | U54: Slightly Above(<=45) | V54: {=_xlfn.IFS(Hospital_Emergency_Room_Data[[#This Row],[Day]]<=10,"Start(1-10)",Hospital_Emergency_Room_Data[[#This Row],[Day]]<=20,"Middle(11-20)",Hospital_Emergency_Room_Data[[#This Row],[Day]]>20,"End(21-30)")} -> Middle(11-20)
A55: 354759525 | B55: L. Shayes | C55: 45560 | D55: =TEXT(Hospital_Emergency_Room_Data[[#This Row],[Patient Admission Date]],"mmm") -> Sep | E55: =YEAR(Hospital_Emergency_Room_Data[[#This Row],[Patient Admission Date]]) -> 2024 | F55: 0.67430556 | G55: =TEXT(Hospital_Emergency_Room_Data[[#This Row],[Patient Admission Date]],"dddd") -> Wednesday | H55: Female | I55: 76 | J55: 70-79 | K55: African American | L55: General Practice | M55: Admitted | O55: 19 | P55: Within Time | Q55: 25 | R55: 16 | S55: 12PM - 6PM | T55: Week 4 | U55: Within Target(<30) | V55: {=_xlfn.IFS(Hospital_Emergency_Room_Data[[#This Row],[Day]]<=10,"Start(1-10)",Hospital_Emergency_Room_Data[[#This Row],[Day]]<=20,"Middle(11-20)",Hospital_Emergency_Room_Data[[#This Row],[Day]]>20,"End(21-30)")} -> End(21-30)
A56: 298722588 | B56: E. Lillistone | C56: 45589 | D56: =TEXT(Hospital_Emergency_Room_Data[[#This Row],[Patient Admission Date]],"mmm") -> Oct | E56: =YEAR(Hospital_Emergency_Room_Data[[#This Row],[Patient Admission Date]]) -> 2024 | F56: 0.20347222 | G56: =TEXT(Hospital_Emergency_Room_Data[[#This Row],[Patient Admission Date]],"dddd") -> Thursday | H56: Male | I56: 74 | J56: 70-79 | K56: Two or More Races | L56: General Practice | M56: Admitted | N56: 9 | O56: 48 | P56: Delay | Q56: 24 | R56: 4 | S56: 12AM - 6AM | T56: Week 4 | U56: Much higher(>45) | V56: {=_xlfn.IFS(Hospital_Emergency_Room_Data[[#This Row],[Day]]<=10,"Start(1-10)",Hospital_Emergency_Room_Data[[#This Row],[Day]]<=20,"Middle(11-20)",Hospital_Emergency_Room_Data[[#This Row],[Day]]>20,"End(21-30)")} -> End(21-30)
A57: 794743955 | B57: E. Cunningham | C57: 45580 | D57: =TEXT(Hospital_Emergency_Room_Data[[#This Row],[Patient Admission Date]],"mmm") -> Oct | E57: =YEAR(Hospital_Emergency_Room_Data[[#This Row],[Patient Admission Date]]) -> 2024 | F57: 0.44513889 | G57: =TEXT(Hospital_Emergency_Room_Data[[#This Row],[Patient Admission Date]],"dddd") -> Tuesday | H57: Male | I57: 15 | J57: 15-29 | K57: Declined to Identify | L57: No Department Assigned | M57: Admitted | O57: 57 | P57: Delay | Q57: 15 | R57: 10 | S57: 6AM - 12PM | T57: Week 3 | U57: Much higher(>45) | V57: {=_xlfn.IFS(Hospital_Emergency_Room_Data[[#This Row],[Day]]<=10,"Start(1-10)",Hospital_Emergency_Room_Data[[#This Row],[Day]]<=20,"Middle(11-20)",Hospital_Emergency_Room_Data[[#This Row],[Day]]>20,"End(21-30)")} -> Middle(11-20)
A58: 213044901 | B58: L. Zum Felde | C58: 45404 | D58: =TEXT(Hospital_Emergency_Room_Data[[#This Row],[Patient Admission Date]],"mmm") -> Apr | E58: =YEAR(Hospital_Emergency_Room_Data[[#This Row],[Patient Admission Date]]) -> 2024 | F58: 0.20763889 | G58: =TEXT(Hospital_Emergency_Room_Data[[#This Row],[Patient Admission Date]],"dddd") -> Monday | H58: Male | I58: 21 | J58: 15-29 | K58: Asian | L58: No Department Assigned | M58: Admitted | O58: 13 | P58: Within Time | Q58: 22 | R58: 4 | S58: 12AM - 6AM | T58: Week 4 | U58: Within Target(<30) | V58: {=_xlfn.IFS(Hospital_Emergency_Room_Data[[#This Row],[Day]]<=10,"Start(1-10)",Hospital_Emergency_Room_Data[[#This Row],[Day]]<=20,"Middle(11-20)",Hospital_Emergency_Room_Data[[#This Row],[Day]]>20,"End(21-30)")} -> End(21-30)
A59: 683465079 | B59: B. Gostridge | C59: 45356 | D59: =TEXT(Hospital_Emergency_Room_Data[[#This Row],[Patient Admission Date]],"mmm") -> Mar | E59: =YEAR(Hospital_Emergency_Room_Data[[#This Row],[Patient Admission Date]]) -> 2024 | F59: 0.58402778 | G59: =TEXT(Hospital_Emergency_Room_Data[[#This Row],[Patient Admission Date]],"dddd") -> Tuesday | H59: Male | I59: 47 | J59: 45-59 | K59: Declined to Identify | L59: General Practice | M59: Not Admitted | O59: 45 | P59: Delay | Q59: 5 | R59: 14 | S59: 12PM - 6PM | T59: Week 1 | U59: Slightly Above(<=45) | V59: {=_xlfn.IFS(Hospital_Emergency_Room_Data[[#This Row],[Day]]<=10,"Start(1-10)",Hospital_Emergency_Room_Data[[#This Row],[Day]]<=20,"Middle(11-20)",Hospital_Emergency_Room_Data[[#This Row],[Day]]>20,"End(21-30)")} -> Start(1-10)
A60: 843560384 | B60: I. Fairrie | C60: 45459 | D60: =TEXT(Hospital_Emergency_Room_Data[[#This Row],[Patient Admission Date]],"mmm") -> Jun | E60: =YEAR(Hospital_Emergency_Room_Data[[#This Row],[Patient Admission Date]]) -> 2024 | F60: 0.70833333 | G60: =TEXT(Hospital_Emergency_Room_Data[[#This Row],[Patient Admission Date]],"dddd") -> Sunday | H60: Male | I60: 60 | J60: 60-69 | K60: Asian | L60: No Department Assigned | M60: Admitted | O60: 41 | P60: Delay | Q60: 16 | R60: 17 | S60: 12PM - 6PM | T60: Week 3 | U60: Slightly Above(<=45) | V60: {=_xlfn.IFS(Hospital_Emergency_Room_Data[[#This Row],[Day]]<=10,"Start(1-10)",Hospital_Emergency_Room_Data[[#This Row],[Day]]<=20,"Middle(11-20)",Hospital_Emergency_Room_Data[[#This Row],[Day]]>20,"End(21-30)")} -> Middle(11-20)
A61: 882391200 | B61: P. Walak | C61: 45188 | D61: =TEXT(Hospital_Emergency_Room_Data[[#This Row],[Patient Admission Date]],"mmm") -> Sep | E61: =YEAR(Hospital_Emergency_Room_Data[[#This Row],[Patient Admission Date]]) -> 2023 | F61: 0.22152778 | G61: =TEXT(Hospital_Emergency_Room_Data[[#This Row],[Patient Admission Date]],"dddd") -> Tuesday | H61: Male | I61: 10 | J61: 5-14 | K61: Two or More Races | L61: Orthopedics | M61: Not Admitted | O61: 55 | P61: Delay | Q61: 19 | R61: 5 | S61: 12AM - 6AM | T61: Week 3 | U61: Much higher(>45) | V61: {=_xlfn.IFS(Hospital_Emergency_Room_Data[[#This Row],[Day]]<=10,"Start(1-10)",Hospital_Emergency_Room_Data[[#This Row],[Day]]<=20,"Middle(11-20)",Hospital_Emergency_Room_Data[[#This Row],[Day]]>20,"End(21-30)")} -> Middle(11-20)
A62: 697903233 | B62: W. Escale | C62: 45374 | D62: =TEXT(Hospital_Emergency_Room_Data[[#This Row],[Patient Admission Date]],"mmm") -> Mar | E62: =YEAR(Hospital_Emergency_Room_Data[[#This Row],[Patient Admission Date]]) -> 2024 | F62: 0.46736111 | G62: =TEXT(Hospital_Emergency_Room_Data[[#This Row],[Patient Admission Date]],"dddd") -> Saturday | H62: Male | I62: 54 | J62: 45-59 | K62: Two or More Races | L62: No Department Assigned | M62: Not Admitted | N62: 10 | O62: 58 | P62: Delay | Q62: 23 | R62: 11 | S62: 6AM - 12PM | T62: Week 4 | U62: Much higher(>45) | V62: {=_xlfn.IFS(Hospital_Emergency_Room_Data[[#This Row],[Day]]<=10,"Start(1-10)",Hospital_Emergency_Room_Data[[#This Row],[Day]]<=20,"Middle(11-20)",Hospital_Emergency_Room_Data[[#This Row],[Day]]>20,"End(21-30)")} -> End(21-30)
A63: 481990791 | B63: Y. Silveston | C63: 45305 | D63: =TEXT(Hospital_Emergency_Room_Data[[#This Row],[Patient Admission Date]],"mmm") -> Jan | E63: =YEAR(Hospital_Emergency_Room_Data[[#This Row],[Patient Admission Date]]) -> 2024 | F63: 0.25486111 | G63: =TEXT(Hospital_Emergency_Room_Data[[#This Row],[Patient Admission Date]],"dddd") -> Sunday | H63: Female | I63: 15 | J63: 15-29 | K63: White | L63: No Department Assigned | M63: Admitted | N63: 7 | O63: 12 | P63: Within Time | Q63: 14 | R63: 6 | S63: 6AM - 12PM | T63: Week 2 | U63: Within Target(<30) | V63: {=_xlfn.IFS(Hospital_Emergency_Room_Data[[#This Row],[Day]]<=10,"Start(1-10)",Hospital_Emergency_Room_Data[[#This Row],[Day]]<=20,"Middle(11-20)",Hospital_Emergency_Room_Data[[#This Row],[Day]]>20,"End(21-30)")} -> Middle(11-20)
A64: 218420736 | B64: T. Dickin | C64: 45408 | D64: =TEXT(Hospital_Emergency_Room_Data[[#This Row],[Patient Admission Date]],"mmm") -> Apr | E64: =YEAR(Hospital_Emergency_Room_Data[[#This Row],[Patient Admission Date]]) -> 2024 | F64: 0.38819444 | G64: =TEXT(Hospital_Emergency_Room_Data[[#This Row],[Patient Admission Date]],"dddd") -> Friday | H64: Male | I64: 55 | J64: 45-59 | K64: Declined to Identify | L64: General Practice | M64: Admitted | O64: 30 | P64: Delay | Q64: 26 | R64: 9 | S64: 6AM - 12PM | T64: Week 4 | U64: Within Target(<30) | V64: {=_xlfn.IFS(Hospital_Emergency_Room_Data[[#This Row],[Day]]<=10,"Start(1-10)",Hospital_Emergency_Room_Data[[#This Row],[Day]]<=20,"Middle(11-20)",Hospital_Emergency_Room_Data[[#This Row],[Day]]>20,"End(21-30)")} -> End(21-30)
A65: 111194529 | B65: Q. Khoter | C65: 45146 | D65: =TEXT(Hospital_Emergency_Room_Data[[#This Row],[Patient Admission Date]],"mmm") -> Aug | E65: =YEAR(Hospital_Emergency_Room_Data[[#This Row],[Patient Admission Date]]) -> 2023 | F65: 0.47430556 | G65: =TEXT(Hospital_Emergency_Room_Data[[#This Row],[Patient Admission Date]],"dddd") -> Tuesday | H65: Male | I65: 11 | J65: 5-14 | K65: White | L65: General Practice | M65: Not Admitted | O65: 48 | P65: Delay | Q65: 8 | R65: 11 | S65: 6AM - 12PM | T65: Week 2 | U65: Much higher(>45) | V65: {=_xlfn.IFS(Hospital_Emergency_Room_Data[[#This Row],[Day]]<=10,"Start(1-10)",Hospital_Emergency_Room_Data[[#This Row],[Day]]<=20,"Middle(11-20)",Hospital_Emergency_Room_Data[[#This Row],[Day]]>20,"End(21-30)")} -> Start(1-10)
A66: 490740642 | B66: F. Deshorts | C66: 45532 | D66: =TEXT(Hospital_Emergency_Room_Data[[#This Row],[Patient Admission Date]],"mmm") -> Aug | E66: =YEAR(Hospital_Emergency_Room_Data[[#This Row],[Patient Admission Date]]) -> 2024 | F66: 0.94444444 | G66: =TEXT(Hospital_Emergency_Room_Data[[#This Row],[Patient Admission Date]],"dddd") -> Wednesday | H66: Male | I66: 7 | J66: 5-14 | K66: Asian | L66: No Department Assigned | M66: Not Admitted | O66: 31 | P66: Delay | Q66: 28 | R66: 22 | S66: 6PM - 12AM | T66: Week 4 | U66: Slightly Above(<=45) | V66: {=_xlfn.IFS(Hospital_Emergency_Room_Data[[#This Row],[Day]]<=10,"Start(1-10)",Hospital_Emergency_Room_Data[[#This Row],[Day]]<=20,"Middle(11-20)",Hospital_Emergency_Room_Data[[#This Row],[Day]]>20,"End(21-30)")} -> End(21-30)
A67: 498998689 | B67: J. McAmish | C67: 45152 | D67: =TEXT(Hospital_Emergency_Room_Data[[#This Row],[Patient Admission Date]],"mmm") -> Aug | E67: =YEAR(Hospital_Emergency_Room_Data[[#This Row],[Patient Admission Date]]) -> 2023 | F67: 0.47361111 | G67: =TEXT(Hospital_Emergency_Room_Data[[#This Row],[Patient Admission Date]],"dddd") -> Monday | H67: Male | I67: 49 | J67: 45-59 | K67: Pacific Islander | L67: No Department Assigned | M67: Admitted | O67: 18 | P67: Within Time | Q67: 14 | R67: 11 | S67: 6AM - 12PM | T67: Week 2 | U67: Within Target(<30) | V67: {=_xlfn.IFS(Hospital_Emergency_Room_Data[[#This Row],[Day]]<=10,"Start(1-10)",Hospital_Emergency_Room_Data[[#This Row],[Day]]<=20,"Middle(11-20)",Hospital_Emergency_Room_Data[[#This Row],[Day]]>20,"End(21-30)")} -> Middle(11-20)
A68: 705012168 | B68: S. Jowitt | C68: 45182 | D68: =TEXT(Hospital_Emergency_Room_Data[[#This Row],[Patient Admission Date]],"mmm") -> Sep | E68: =YEAR(Hospital_Emergency_Room_Data[[#This Row],[Patient Admission Date]]) -> 2023 | F68: 0.87152778 | G68: =TEXT(Hospital_Emergency_Room_Data[[#This Row],[Patient Admission Date]],"dddd") -> Wednesday | H68: Female | I68: 70 | J68: 70-79 | K68: African American | L68: General Practice | M68: Admitted | O68: 55 | P68: Delay | Q68: 13 | R68: 20 | S68: 6PM - 12AM | T68: Week 2 | U68: Much higher(>45) | V68: {=_xlfn.IFS(Hospital_Emergency_Room_Data[[#This Row],[Day]]<=10,"Start(1-10)",Hospital_Emergency_Room_Data[[#This Row],[Day]]<=20,"Middle(11-20)",Hospital_Emergency_Room_Data[[#This Row],[Day]]>20,"End(21-30)")} -> Middle(11-20)
A69: 119285124 | B69: O. Pocklington | C69: 45034 | D69: =TEXT(Hospital_Emergency_Room_Data[[#This Row],[Patient Admission Date]],"mmm") -> Apr | E69: =YEAR(Hospital_Emergency_Room_Data[[#This Row],[Patient Admission Date]]) -> 2023 | F69: 0.62291667 | G69: =TEXT(Hospital_Emergency_Room_Data[[#This Row],[Patient Admission Date]],"dddd") -> Tuesday | H69: Female | I69: 16 | J69: 15-29 | K69: Asian | L69: General Practice | M69: Admitted | O69: 51 | P69: Delay | Q69: 18 | R69: 14 | S69: 12PM - 6PM | T69: Week 3 | U69: Much higher(>45) | V69: {=_xlfn.IFS(Hospital_Emergency_Room_Data[[#This Row],[Day]]<=10,"Start(1-10)",Hospital_Emergency_Room_Data[[#This Row],[Day]]<=20,"Middle(11-20)",Hospital_Emergency_Room_Data[[#This Row],[Day]]>20,"End(21-30)")} -> Middle(11-20)
A70: 509882899 | B70: F. Brudenell | C70: 45192 | D70: =TEXT(Hospital_Emergency_Room_Data[[#This Row],[Patient Admission Date]],"mmm") -> Sep | E70: =YEAR(Hospital_Emergency_Room_Data[[#This Row],[Patient Admission Date]]) -> 2023 | F70: 0.99375 | G70: =TEXT(Hospital_Emergency_Room_Data[[#This Row],[Patient Admission Date]],"dddd") -> Saturday | H70: Male | I70: 14 | J70: 5-14 | K70: Two or More Races | L70: Orthopedics | M70: Admitted | N70: 4 | O70: 23 | P70: Within Time | Q70: 23 | R70: 23 | S70: 6PM - 12AM | T70: Week 4 | U70: Within Target(<30) | V70: {=_xlfn.IFS(Hospital_Emergency_Room_Data[[#This Row],[Day]]<=10,"Start(1-10)",Hospital_Emergency_Room_Data[[#This Row],[Day]]<=20,"Middle(11-20)",Hospital_Emergency_Room_Data[[#This Row],[Day]]>20,"End(21-30)")} -> End(21-30)
A71: 258482258 | B71: T. Lyons | C71: 45099 | D71: =TEXT(Hospital_Emergency_Room_Data[[#This Row],[Patient Admission Date]],"mmm") -> Jun | E71: =YEAR(Hospital_Emergency_Room_Data[[#This Row],[Patient Admission Date]]) -> 2023 | F71: 0.98125 | G71: =TEXT(Hospital_Emergency_Room_Data[[#This Row],[Patient Admission Date]],"dddd") -> Thursday | H71: Male | I71: 41 | J71: 30-45 | K71: African American | L71: No Department Assigned | M71: Not Admitted | N71: 4 | O71: 46 | P71: Delay | Q71: 22 | R71: 23 | S71: 6PM - 12AM | T71: Week 4 | U71: Much higher(>45) | V71: {=_xlfn.IFS(Hospital_Emergency_Room_Data[[#This Row],[Day]]<=10,"Start(1-10)",Hospital_Emergency_Room_Data[[#This Row],[Day]]<=20,"Middle(11-20)",Hospital_Emergency_Room_Data[[#This Row],[Day]]>20,"End(21-30)")} -> End(21-30)
A72: 369335075 | B72: H. Esposi | C72: 45219 | D72: =TEXT(Hospital_Emergency_Room_Data[[#This Row],[Patient Admission Date]],"mmm") -> Oct | E72: =YEAR(Hospital_Emergency_Room_Data[[#This Row],[Patient Admission Date]]) -> 2023 | F72: 0.033333333 | G72: =TEXT(Hospital_Emergency_Room_Data[[#This Row],[Patient Admission Date]],"dddd") -> Friday | H72: Male | I72: 8 | J72: 5-14 | K72: African American | L72: No Department Assigned | M72: Not Admitted | O72: 37 | P72: Delay | Q72: 20 | R72: 0 | S72: 12AM - 6AM | T72: Week 3 | U72: Slightly Above(<=45) | V72: {=_xlfn.IFS(Hospital_Emergency_Room_Data[[#This Row],[Day]]<=10,"Start(1-10)",Hospital_Emergency_Room_Data[[#This Row],[Day]]<=20,"Middle(11-20)",Hospital_Emergency_Room_Data[[#This Row],[Day]]>20,"End(21-30)")} -> Middle(11-20)
A73: 643903414 | B73: U. Mangham | C73: 45573 | D73: =TEXT(Hospital_Emergency_Room_Data[[#This Row],[Patient Admission Date]],"mmm") -> Oct | E73: =YEAR(Hospital_Emergency_Room_Data[[#This Row],[Patient Admission Date]]) -> 2024 | F73: 0.66041667 | G73: =TEXT(Hospital_Emergency_Room_Data[[#This Row],[Patient Admission Date]],"dddd") -> Tuesday | H73: Male | I73: 64 | J73: 60-69 | K73: Pacific Islander | L73: No Department Assigned | M73: Not Admitted | O73: 59 | P73: Delay | Q73: 8 | R73: 15 | S73: 12PM - 6PM | T73: Week 2 | U73: Much higher(>45) | V73: {=_xlfn.IFS(Hospital_Emergency_Room_Data[[#This Row],[Day]]<=10,"Start(1-10)",Hospital_Emergency_Room_Data[[#This Row],[Day]]<=20,"Middle(11-20)",Hospital_Emergency_Room_Data[[#This Row],[Day]]>20,"End(21-30)")} -> Start(1-10)
A74: 412296293 | B74: J. Gianneschi | C74: 45423 | D74: =TEXT(Hospital_Emergency_Room_Data[[#This Row],[Patient Admission Date]],"mmm") -> May | E74: =YEAR(Hospital_Emergency_Room_Data[[#This Row],[Patient Admission Date]]) -> 2024 | F74: 0.66111111 | G74: =TEXT(Hospital_Emergency_Room_Data[[#This Row],[Patient Admission Date]],"dddd") -> Saturday | H74: Female | I74: 76 | J74: 70-79 | K74: Two or More Races | L74: Gastroenterology | M74: Admitted | O74: 34 | P74: Delay | Q74: 11 | R74: 15 | S74: 12PM - 6PM | T74: Week 2 | U74: Slightly Above(<=45) | V74: {=_xlfn.IFS(Hospital_Emergency_Room_Data[[#This Row],[Day]]<=10,"Start(1-10)",Hospital_Emergency_Room_Data[[#This Row],[Day]]<=20,"Middle(11-20)",Hospital_Emergency_Room_Data[[#This Row],[Day]]>20,"End(21-30)")} -> Middle(11-20)
A75: 844819989 | B75: C. Veldens | C75: 45373 | D75: =TEXT(Hospital_Emergency_Room_Data[[#This Row],[Patient Admission Date]],"mmm") -> Mar | E75: =YEAR(Hospital_Emergency_Room_Data[[#This Row],[Patient Admission Date]]) -> 2024 | F75: 0.11666667 | G75: =TEXT(Hospital_Emergency_Room_Data[[#This Row],[Patient Admission Date]],"dddd") -> Friday | H75: Female | I75: 17 | J75: 15-29 | K75: African American | L75: General Practice | M75: Admitted | O75: 27 | P75: Within Time | Q75: 22 | R75: 2 | S75: 12AM - 6AM | T75: Week 4 | U75: Within Target(<30) | V75: {=_xlfn.IFS(Hospital_Emergency_Room_Data[[#This Row],[Day]]<=10,"Start(1-10)",Hospital_Emergency_Room_Data[[#This Row],[Day]]<=20,"Middle(11-20)",Hospital_Emergency_Room_Data[[#This Row],[Day]]>20,"End(21-30)")} -> End(21-30)
A76: 839138580 | B76: X. Barbery | C76: 45174 | D76: =TEXT(Hospital_Emergency_Room_Data[[#This Row],[Patient Admission Date]],"mmm") -> Sep | E76: =YEAR(Hospital_Emergency_Room_Data[[#This Row],[Patient Admission Date]]) -> 2023 | F76: 0.42916667 | G76: =TEXT(Hospital_Emergency_Room_Data[[#This Row],[Patient Admission Date]],"dddd") -> Tuesday | H76: Male | I76: 38 | J76: 30-45 | K76: Two or More Races | L76: No Department Assigned | M76: Not Admitted | O76: 55 | P76: Delay | Q76: 5 | R76: 10 | S76: 6AM - 12PM | T76: Week 1 | U76: Much higher(>45) | V76: {=_xlfn.IFS(Hospital_Emergency_Room_Data[[#This Row],[Day]]<=10,"Start(1-10)",Hospital_Emergency_Room_Data[[#This Row],[Day]]<=20,"Middle(11-20)",Hospital_Emergency_Room_Data[[#This Row],[Day]]>20,"End(21-30)")} -> Start(1-10)
A77: 367529587 | B77: R. Millan | C77: 45110 | D77: =TEXT(Hospital_Emergency_Room_Data[[#This Row],[Patient Admission Date]],"mmm") -> Jul | E77: =YEAR(Hospital_Emergency_Room_Data[[#This Row],[Patient Admission Date]]) -> 2023 | F77: 0.85208333 | G77: =TEXT(Hospital_Emergency_Room_Data[[#This Row],[Patient Admission Date]],"dddd") -> Monday | H77: Female | I77: 75 | J77: 70-79 | K77: White | L77: Cardiology | M77: Admitted | O77: 34 | P77: Delay | Q77: 3 | R77: 20 | S77: 6PM - 12AM | T77: Week 1 | U77: Slightly Above(<=45) | V77: {=_xlfn.IFS(Hospital_Emergency_Room_Data[[#This Row],[Day]]<=10,"Start(1-10)",Hospital_Emergency_Room_Data[[#This Row],[Day]]<=20,"Middle(11-20)",Hospital_Emergency_Room_Data[[#This Row],[Day]]>20,"End(21-30)")} -> Start(1-10)
A78: 621856677 | B78: X. Klimowicz | C78: 45420 | D78: =TEXT(Hospital_Emergency_Room_Data[[#This Row],[Patient Admission Date]],"mmm") -> May | E78: =YEAR(Hospital_Emergency_Room_Data[[#This Row],[Patient Admission Date]]) -> 2024 | F78: 0.75208333 | G78: =TEXT(Hospital_Emergency_Room_Data[[#This Row],[Patient Admission Date]],"dddd") -> Wednesday | H78: Male | I78: 77 | J78: 70-79 | K78: Native American/Alaska Native | L78: General Practice | M78: Not Admitted | N78: 0 | O78: 17 | P78: Within Time | Q78: 8 | R78: 18 | S78: 6PM - 12AM | T78: Week 2 | U78: Within Target(<30) | V78: {=_xlfn.IFS(Hospital_Emergency_Room_Data[[#This Row],[Day]]<=10,"Start(1-10)",Hospital_Emergency_Room_Data[[#This Row],[Day]]<=20,"Middle(11-20)",Hospital_Emergency_Room_Data[[#This Row],[Day]]>20,"End(21-30)")} -> Start(1-10)
A79: 563012494 | B79: D. Blaasch | C79: 45297 | D79: =TEXT(Hospital_Emergency_Room_Data[[#This Row],[Patient Admission Date]],"mmm") -> Jan | E79: =YEAR(Hospital_Emergency_Room_Data[[#This Row],[Patient Admission Date]]) -> 2024 | F79: 0.86111111 | G79: =TEXT(Hospital_Emergency_Room_Data[[#This Row],[Patient Admission Date]],"dddd") -> Saturday | H79: Male | I79: 34 | J79: 30-45 | K79: Asian | L79: No Department Assigned | M79: Admitted | O79: 40 | P79: Delay | Q79: 6 | R79: 20 | S79: 6PM - 12AM | T79: Week 1 | U79: Slightly Above(<=45) | V79: {=_xlfn.IFS(Hospital_Emergency_Room_Data[[#This Row],[Day]]<=10,"Start(1-10)",Hospital_Emergency_Room_Data[[#This Row],[Day]]<=20,"Middle(11-20)",Hospital_Emergency_Room_Data[[#This Row],[Day]]>20,"End(21-30)")} -> Start(1-10)
A80: 570113903 | B80: X. Audiss | C80: 45358 | D80: =TEXT(Hospital_Emergency_Room_Data[[#This Row],[Patient Admission Date]],"mmm") -> Mar | E80: =YEAR(Hospital_Emergency_Room_Data[[#This Row],[Patient Admission Date]]) -> 2024 | F80: 0.41666667 | G80: =TEXT(Hospital_Emergency_Room_Data[[#This Row],[Patient Admission Date]],"dddd") -> Thursday | H80: Female | I80: 26 | J80: 15-29 | K80: Asian | L80: Cardiology | M80: Admitted | N80: 1 | O80: 16 | P80: Within Time | Q80: 7 | R80: 10 | S80: 6AM - 12PM | T80: Week 1 | U80: Within Target(<30) | V80: {=_xlfn.IFS(Hospital_Emergency_Room_Data[[#This Row],[Day]]<=10,"Start(1-10)",Hospital_Emergency_Room_Data[[#This Row],[Day]]<=20,"Middle(11-20)",Hospital_Emergency_Room_Data[[#This Row],[Day]]>20,"End(21-30)")} -> Start(1-10)
A81: 292458684 | B81: K. Hilliam | C81: 45033 | D81: =TEXT(Hospital_Emergency_Room_Data[[#This Row],[Patient Admission Date]],"mmm") -> Apr | E81: =YEAR(Hospital_Emergency_Room_Data[[#This Row],[Patient Admission Date]]) -> 2023 | F81: 0.48402778 | G81: =TEXT(Hospital_Emergency_Room_Data[[#This Row],[Patient Admission Date]],"dddd") -> Monday | H81: Female | I81: 51 | J81: 45-59 | K81: White | L81: General Practice | M81: Admitted | N81: 6 | O81: 25 | P81: Within Time | Q81: 17 | R81: 11 | S81: 6AM - 12PM | T81: Week 3 | U81: Within Target(<30) | V81: {=_xlfn.IFS(Hospital_Emergency_Room_Data[[#This Row],[Day]]<=10,"Start(1-10)",Hospital_Emergency_Room_Data[[#This Row],[Day]]<=20,"Middle(11-20)",Hospital_Emergency_Room_Data[[#This Row],[Day]]>20,"End(21-30)")} -> Middle(11-20)
A82: 721193123 | B82: I. Franzelini | C82: 45126 | D82: =TEXT(Hospital_Emergency_Room_Data[[#This Row],[Patient Admission Date]],"mmm") -> Jul | E82: =YEAR(Hospital_Emergency_Room_Data[[#This Row],[Patient Admission Date]]) -> 2023 | F82: 0.14097222 | G82: =TEXT(Hospital_Emergency_Room_Data[[#This Row],[Patient Admission Date]],"dddd") -> Wednesday | H82: Female | I82: 9 | J82: 5-14 | K82: African American | L82: No Department Assigned | M82: Not Admitted | O82: 23 | P82: Within Time | Q82: 19 | R82: 3 | S82: 12AM - 6AM | T82: Week 3 | U82: Within Target(<30) | V82: {=_xlfn.IFS(Hospital_Emergency_Room_Data[[#This Row],[Day]]<=10,"Start(1-10)",Hospital_Emergency_Room_Data[[#This Row],[Day]]<=20,"Middle(11-20)",Hospital_Emergency_Room_Data[[#This Row],[Day]]>20,"End(21-30)")} -> Middle(11-20)
A83: 652339813 | B83: D. Hovie | C83: 45458 | D83: =TEXT(Hospital_Emergency_Room_Data[[#This Row],[Patient Admission Date]],"mmm") -> Jun | E83: =YEAR(Hospital_Emergency_Room_Data[[#This Row],[Patient Admission Date]]) -> 2024 | F83: 0.15694444 | G83: =TEXT(Hospital_Emergency_Room_Data[[#This Row],[Patient Admission Date]],"dddd") -> Saturday | H83: Female | I83: 71 | J83: 70-79 | K83: Two or More Races | L83: No Department Assigned | M83: Admitted | O83: 51 | P83: Delay | Q83: 15 | R83: 3 | S83: 12AM - 6AM | T83: Week 3 | U83: Much higher(>45) | V83: {=_xlfn.IFS(Hospital_Emergency_Room_Data[[#This Row],[Day]]<=10,"Start(1-10)",Hospital_Emergency_Room_Data[[#This Row],[Day]]<=20,"Middle(11-20)",Hospital_Emergency_Room_Data[[#This Row],[Day]]>20,"End(21-30)")} -> Middle(11-20)
A84: 809146629 | B84: N. Kinmond | C84: 45247 | D84: =TEXT(Hospital_Emergency_Room_Data[[#This Row],[Patient Admission Date]],"mmm") -> Nov | E84: =YEAR(Hospital_Emergency_Room_Data[[#This Row],[Patient Admission Date]]) -> 2023 | F84: 0.26597222 | G84: =TEXT(Hospital_Emergency_Room_Data[[#This Row],[Patient Admission Date]],"dddd") -> Friday | H84: Male | I84: 51 | J84: 45-59 | K84: African American | L84: No Department Assigned | M84: Not Admitted | O84: 33 | P84: Delay | Q84: 17 | R84: 6 | S84: 6AM - 12PM | T84: Week 3 | U84: Slightly Above(<=45) | V84: {=_xlfn.IFS(Hospital_Emergency_Room_Data[[#This Row],[Day]]<=10,"Start(1-10)",Hospital_Emergency_Room_Data[[#This Row],[Day]]<=20,"Middle(11-20)",Hospital_Emergency_Room_Data[[#This Row],[Day]]>20,"End(21-30)")} -> Middle(11-20)
A85: 304723326 | B85: O. Brito | C85: 45456 | D85: =TEXT(Hospital_Emergency_Room_Data[[#This Row],[Patient Admission Date]],"mmm") -> Jun | E85: =YEAR(Hospital_Emergency_Room_Data[[#This Row],[Patient Admission Date]]) -> 2024 | F85: 0.84375 | G85: =TEXT(Hospital_Emergency_Room_Data[[#This Row],[Patient Admission Date]],"dddd") -> Thursday | H85: Female | I85: 73 | J85: 70-79 | K85: Asian | L85: Gastroenterology | M85: Not Admitted | N85: 0 | O85: 10 | P85: Within Time | Q85: 13 | R85: 20 | S85: 6PM - 12AM | T85: Week 2 | U85: Within Target(<30) | V85: {=_xlfn.IFS(Hospital_Emergency_Room_Data[[#This Row],[Day]]<=10,"Start(1-10)",Hospital_Emergency_Room_Data[[#This Row],[Day]]<=20,"Middle(11-20)",Hospital_Emergency_Room_Data[[#This Row],[Day]]>20,"End(21-30)")} -> Middle(11-20)
A86: 231207799 | B86: V. Puddifer | C86: 45079 | D86: =TEXT(Hospital_Emergency_Room_Data[[#This Row],[Patient Admission Date]],"mmm") -> Jun | E86: =YEAR(Hospital_Emergency_Room_Data[[#This Row],[Patient Admission Date]]) -> 2023 | F86: 0.32222222 | G86: =TEXT(Hospital_Emergency_Room_Data[[#This Row],[Patient Admission Date]],"dddd") -> Friday | H86: Female | I86: 46 | J86: 45-59 | K86: White | L86: Physiotherapy | M86: Not Admitted | N86: 5 | O86: 50 | P86: Delay | Q86: 2 | R86: 7 | S86: 6AM - 12PM | T86: Week 1 | U86: Much higher(>45) | V86: {=_xlfn.IFS(Hospital_Emergency_Room_Data[[#This Row],[Day]]<=10,"Start(1-10)",Hospital_Emergency_Room_Data[[#This Row],[Day]]<=20,"Middle(11-20)",Hospital_Emergency_Room_Data[[#This Row],[Day]]>20,"End(21-30)")} -> Start(1-10)
A87: 597410817 | B87: T. Titman | C87: 45033 | D87: =TEXT(Hospital_Emergency_Room_Data[[#This Row],[Patient Admission Date]],"mmm") -> Apr | E87: =YEAR(Hospital_Emergency_Room_Data[[#This Row],[Patient Admission Date]]) -> 2023 | F87: 0.33541667 | G87: =TEXT(Hospital_Emergency_Room_Data[[#This Row],[Patient Admission Date]],"dddd") -> Monday | H87: Female | I87: 13 | J87: 5-14 | K87: White | L87: No Department Assigned | M87: Admitted | N87: 1 | O87: 32 | P87: Delay | Q87: 17 | R87: 8 | S87: 6AM - 12PM | T87: Week 3 | U87: Slightly Above(<=45) | V87: {=_xlfn.IFS(Hospital_Emergency_Room_Data[[#This Row],[Day]]<=10,"Start(1-10)",Hospital_Emergency_Room_Data[[#This Row],[Day]]<=20,"Middle(11-20)",Hospital_Emergency_Room_Data[[#This Row],[Day]]>20,"End(21-30)")} -> Middle(11-20)
A88: 496239655 | B88: X. Maffin | C88: 45210 | D88: =TEXT(Hospital_Emergency_Room_Data[[#This Row],[Patient Admission Date]],"mmm") -> Oct | E88: =YEAR(Hospital_Emergency_Room_Data[[#This Row],[Patient Admission Date]]) -> 2023 | F88: 0.14166667 | G88: =TEXT(Hospital_Emergency_Room_Data[[#This Row],[Patient Admission Date]],"dddd") -> Wednesday | H88: Female | I88: 15 | J88: 15-29 | K88: Declined to Identify | L88: General Practice | M88: Admitted | N88: 9 | O88: 15 | P88: Within Time | Q88: 11 | R88: 3 | S88: 12AM - 6AM | T88: Week 2 | U88: Within Target(<30) | V88: {=_xlfn.IFS(Hospital_Emergency_Room_Data[[#This Row],[Day]]<=10,"Start(1-10)",Hospital_Emergency_Room_Data[[#This Row],[Day]]<=20,"Middle(11-20)",Hospital_Emergency_Room_Data[[#This Row],[Day]]>20,"End(21-30)")} -> Middle(11-20)
A89: 636906357 | B89: B. Lambarth | C89: 45216 | D89: =TEXT(Hospital_Emergency_Room_Data[[#This Row],[Patient Admission Date]],"mmm") -> Oct | E89: =YEAR(Hospital_Emergency_Room_Data[[#This Row],[Patient Admission Date]]) -> 2023 | F89: 0.56111111 | G89: =TEXT(Hospital_Emergency_Room_Data[[#This Row],[Patient Admission Date]],"dddd") -> Tuesday | H89: Male | I89: 57 | J89: 45-59 | K89: White | L89: General Practice | M89: Admitted | N89: 2 | O89: 35 | P89: Delay | Q89: 17 | R89: 13 | S89: 12PM - 6PM | T89: Week 3 | U89: Slightly Above(<=45) | V89: {=_xlfn.IFS(Hospital_Emergency_Room_Data[[#This Row],[Day]]<=10,"Start(1-10)",Hospital_Emergency_Room_Data[[#This Row],[Day]]<=20,"Middle(11-20)",Hospital_Emergency_Room_Data[[#This Row],[Day]]>20,"End(21-30)")} -> Middle(11-20)
A90: 300342747 | B90: B. Durrant | C90: 45270 | D90: =TEXT(Hospital_Emergency_Room_Data[[#This Row],[Patient Admission Date]],"mmm") -> Dec | E90: =YEAR(Hospital_Emergency_Room_Data[[#This Row],[Patient Admission Date]]) -> 2023 | F90: 0.88333333 | G90: =TEXT(Hospital_Emergency_Room_Data[[#This Row],[Patient Admission Date]],"dddd") -> Sunday | H90: Male | I90: 16 | J90: 15-29 | K90: Pacific Islander | L90: No Department Assigned | M90: Admitted | N90: 4 | O90: 34 | P90: Delay | Q90: 10 | R90: 21 | S90: 6PM - 12AM | T90: Week 2 | U90: Slightly Above(<=45) | V90: {=_xlfn.IFS(Hospital_Emergency_Room_Data[[#This Row],[Day]]<=10,"Start(1-10)",Hospital_Emergency_Room_Data[[#This Row],[Day]]<=20,"Middle(11-20)",Hospital_Emergency_Room_Data[[#This Row],[Day]]>20,"End(21-30)")} -> Start(1-10)
A91: 178521500 | B91: K. Beavington | C91: 45472 | D91: =TEXT(Hospital_Emergency_Room_Data[[#This Row],[Patient Admission Date]],"mmm") -> Jun | E91: =YEAR(Hospital_Emergency_Room_Data[[#This Row],[Patient Admission Date]]) -> 2024 | F91: 0.60208333 | G91: =TEXT(Hospital_Emergency_Room_Data[[#This Row],[Patient Admission Date]],"dddd") -> Saturday | H91: Male | I91: 4 | J91: 0-5 | K91: White | L91: Orthopedics | M91: Not Admitted | O91: 59 | P91: Delay | Q91: 29 | R91: 14 | S91: 12PM - 6PM | T91: Week 4 | U91: Much higher(>45) | V91: {=_xlfn.IFS(Hospital_Emergency_Room_Data[[#This Row],[Day]]<=10,"Start(1-10)",Hospital_Emergency_Room_Data[[#This Row],[Day]]<=20,"Middle(11-20)",Hospital_Emergency_Room_Data[[#This Row],[Day]]>20,"End(21-30)")} -> End(21-30)
A92: 521841782 | B92: A. Fidal | C92: 45249 | D92: =TEXT(Hospital_Emergency_Room_Data[[#This Row],[Patient Admission Date]],"mmm") -> Nov | E92: =YEAR(Hospital_Emergency_Room_Data[[#This Row],[Patient Admission Date]]) -> 2023 | F92: 0.82222222 | G92: =TEXT(Hospital_Emergency_Room_Data[[#This Row],[Patient Admission Date]],"dddd") -> Sunday | H92: Female | I92: 32 | J92: 30-45 | K92: African American | L92: No Department Assigned | M92: Not Admitted | N92: 7 | O92: 14 | P92: Within Time | Q92: 19 | R92: 19 | S92: 6PM - 12AM | T92: Week 3 | U92: Within Target(<30) | V92: {=_xlfn.IFS(Hospital_Emergency_Room_Data[[#This Row],[Day]]<=10,"Start(1-10)",Hospital_Emergency_Room_Data[[#This Row],[Day]]<=20,"Middle(11-20)",Hospital_Emergency_Room_Data[[#This Row],[Day]]>20,"End(21-30)")} -> Middle(11-20)
A93: 818268196 | B93: B. MacNally | C93: 45553 | D93: =TEXT(Hospital_Emergency_Room_Data[[#This Row],[Patient Admission Date]],"mmm") -> Sep | E93: =YEAR(Hospital_Emergency_Room_Data[[#This Row],[Patient Admission Date]]) -> 2024 | F93: 0.74236111 | G93: =TEXT(Hospital_Emergency_Room_Data[[#This Row],[Patient Admission Date]],"dddd") -> Wednesday | H93: Male | I93: 26 | J93: 15-29 | K93: African American | L93: Orthopedics | M93: Admitted | N93: 8 | O93: 38 | P93: Delay | Q93: 18 | R93: 17 | S93: 12PM - 6PM | T93: Week 3 | U93: Slightly Above(<=45) | V93: {=_xlfn.IFS(Hospital_Emergency_Room_Data[[#This Row],[Day]]<=10,"Start(1-10)",Hospital_Emergency_Room_Data[[#This Row],[Day]]<=20,"Middle(11-20)",Hospital_Emergency_Room_Data[[#This Row],[Day]]>20,"End(21-30)")} -> Middle(11-20)
A94: 808115508 | B94: U. Peat | C94: 45590 | D94: =TEXT(Hospital_Emergency_Room_Data[[#This Row],[Patient Admission Date]],"mmm") -> Oct | E94: =YEAR(Hospital_Emergency_Room_Data[[#This Row],[Patient Admission Date]]) -> 2024 | F94: 0.43958333 | G94: =TEXT(Hospital_Emergency_Room_Data[[#This Row],[Patient Admission Date]],"dddd") -> Friday | H94: Female | I94: 9 | J94: 5-14 | K94: Declined to Identify | L94: Neurology | M94: Admitted | O94: 37 | P94: Delay | Q94: 25 | R94: 10 | S94: 6AM - 12PM | T94: Week 4 | U94: Slightly Above(<=45) | V94: {=_xlfn.IFS(Hospital_Emergency_Room_Data[[#This Row],[Day]]<=10,"Start(1-10)",Hospital_Emergency_Room_Data[[#This Row],[Day]]<=20,"Middle(11-20)",Hospital_Emergency_Room_Data[[#This Row],[Day]]>20,"End(21-30)")} -> End(21-30)
A95: 439252191 | B95: M. Plews | C95: 45575 | D95: =TEXT(Hospital_Emergency_Room_Data[[#This Row],[Patient Admission Date]],"mmm") -> Oct | E95: =YEAR(Hospital_Emergency_Room_Data[[#This Row],[Patient Admission Date]]) -> 2024 | F95: 0.18680556 | G95: =TEXT(Hospital_Emergency_Room_Data[[#This Row],[Patient Admission Date]],"dddd") -> Thursday | H95: Female | I95: 10 | J95: 5-14 | K95: White | L95: General Practice | M95: Admitted | O95: 26 | P95: Within Time | Q95: 10 | R95: 4 | S95: 12AM - 6AM | T95: Week 2 | U95: Within Target(<30) | V95: {=_xlfn.IFS(Hospital_Emergency_Room_Data[[#This Row],[Day]]<=10,"Start(1-10)",Hospital_Emergency_Room_Data[[#This Row],[Day]]<=20,"Middle(11-20)",Hospital_Emergency_Room_Data[[#This Row],[Day]]>20,"End(21-30)")} -> Start(1-10)
A96: 186285457 | B96: L. Downing | C96: 45579 | D96: =TEXT(Hospital_Emergency_Room_Data[[#This Row],[Patient Admission Date]],"mmm") -> Oct | E96: =YEAR(Hospital_Emergency_Room_Data[[#This Row],[Patient Admission Date]]) -> 2024 | F96: 0.25208333 | G96: =TEXT(Hospital_Emergency_Room_Data[[#This Row],[Patient Admission Date]],"dddd") -> Monday | H96: Female | I96: 24 | J96: 15-29 | K96: Two or More Races | L96: General Practice | M96: Admitted | O96: 11 | P96: Within Time | Q96: 14 | R96: 6 | S96: 6AM - 12PM | T96: Week 2 | U96: Within Target(<30) | V96: {=_xlfn.IFS(Hospital_Emergency_Room_Data[[#This Row],[Day]]<=10,"Start(1-10)",Hospital_Emergency_Room_Data[[#This Row],[Day]]<=20,"Middle(11-20)",Hospital_Emergency_Room_Data[[#This Row],[Day]]>20,"End(21-30)")} -> Middle(11-20)
A97: 854613541 | B97: U. Lightman | C97: 45525 | D97: =TEXT(Hospital_Emergency_Room_Data[[#This Row],[Patient Admission Date]],"mmm") -> Aug | E97: =YEAR(Hospital_Emergency_Room_Data[[#This Row],[Patient Admission Date]]) -> 2024 | F97: 0.042361111 | G97: =TEXT(Hospital_Emergency_Room_Data[[#This Row],[Patient Admission Date]],"dddd") -> Wednesday | H97: Male | I97: 27 | J97: 15-29 | K97: White | L97: No Department Assigned | M97: Not Admitted | O97: 11 | P97: Within Time | Q97: 21 | R97: 1 | S97: 12AM - 6AM | T97: Week 3 | U97: Within Target(<30) | V97: {=_xlfn.IFS(Hospital_Emergency_Room_Data[[#This Row],[Day]]<=10,"Start(1-10)",Hospital_Emergency_Room_Data[[#This Row],[Day]]<=20,"Middle(11-20)",Hospital_Emergency_Room_Data[[#This Row],[Day]]>20,"End(21-30)")} -> End(21-30)
A98: 368534901 | B98: I. Rubinsztein | C98: 45535 | D98: =TEXT(Hospital_Emergency_Room_Data[[#This Row],[Patient Admission Date]],"mmm") -> Aug | E98: =YEAR(Hospital_Emergency_Room_Data[[#This Row],[Patient Admission Date]]) -> 2024 | F98: 0.27638889 | G98: =TEXT(Hospital_Emergency_Room_Data[[#This Row],[Patient Admission Date]],"dddd") -> Saturday | H98: Male | I98: 26 | J98: 15-29 | K98: White | L98: No Department Assigned | M98: Not Admitted | N98: 7 | O98: 59 | P98: Delay | Q98: 31 | R98: 6 | S98: 6AM - 12PM | T98: Week 4 | U98: Much higher(>45) | V98: {=_xlfn.IFS(Hospital_Emergency_Room_Data[[#This Row],[Day]]<=10,"Start(1-10)",Hospital_Emergency_Room_Data[[#This Row],[Day]]<=20,"Middle(11-20)",Hospital_Emergency_Room_Data[[#This Row],[Day]]>20,"End(21-30)")} -> End(21-30)
A99: 826271762 | B99: I. Melluish | C99: 45511 | D99: =TEXT(Hospital_Emergency_Room_Data[[#This Row],[Patient Admission Date]],"mmm") -> Aug | E99: =YEAR(Hospital_Emergency_Room_Data[[#This Row],[Patient Admission Date]]) -> 2024 | F99: 0.56458333 | G99: =TEXT(Hospital_Emergency_Room_Data[[#This Row],[Patient Admission Date]],"dddd") -> Wednesday | H99: Male | I99: 79 | J99: 70-79 | K99: African American | L99: No Department Assigned | M99: Not Admitted | O99: 29 | P99: Within Time | Q99: 7 | R99: 13 | S99: 12PM - 6PM | T99: Week 1 | U99: Within Target(<30) | V99: {=_xlfn.IFS(Hospital_Emergency_Room_Data[[#This Row],[Day]]<=10,"Start(1-10)",Hospital_Emergency_Room_Data[[#This Row],[Day]]<=20,"Middle(11-20)",Hospital_Emergency_Room_Data[[#This Row],[Day]]>20,"End(21-30)")} -> Start(1-10)
A100: 335732892 | B100: Y. Ricks | C100: 45164 | D100: =TEXT(Hospital_Emergency_Room_Data[[#This Row],[Patient Admission Date]],"mmm") -> Aug | E100: =YEAR(Hospital_Emergency_Room_Data[[#This Row],[Patient Admission Date]]) -> 2023 | F100: 0.35555556 | G100: =TEXT(Hospital_Emergency_Room_Data[[#This Row],[Patient Admission Date]],"dddd") -> Saturday | H100: Male | I100: 15 | J100: 15-29 | K100: Asian | L100: General Practice | M100: Admitted | N100: 2 | O100: 56 | P100: Delay | Q100: 26 | R100: 8 | S100: 6AM - 12PM | T100: Week 4 | U100: Much higher(>45) | V100: {=_xlfn.IFS(Hospital_Emergency_Room_Data[[#This Row],[Day]]<=10,"Start(1-10)",Hospital_Emergency_Room_Data[[#This Row],[Day]]<=20,"Middle(11-20)",Hospital_Emergency_Room_Data[[#This Row],[Day]]>20,"End(21-30)")} -> End(21-30)
...

Sheet Final Dashboard
E10: Admitted | G10: Not admitted | I10: Total Patients | K10: Avg Satisfaction Score | O10: Avg Wait Time
E13: =GETPIVOTDATA("Count of Patient Id",'KPI''s'!$B$2,"Patient Admission Flag","Admitted") -> 4612 | G13: =GETPIVOTDATA("Count of Patient Id",'KPI''s'!$B$2,"Patient Admission Flag","Not Admitted") -> 4604 | I13: =GETPIVOTDATA("Count of Patient Id",'KPI''s'!$B$2) -> 9216 | K13: =GETPIVOTDATA("Average of Patient Satisfaction Score",'KPI''s'!$B$2) -> 4.992054 | O13: =GETPIVOTDATA("Average of Patient Wait time",'KPI''s'!$B$2) -> 35.259874

Sheet KPI's
C2: Column Labels | O2: Row Labels | P2: Count of Patient Id
C3: Admitted | F3: Not Admitted | I3: Total Count of Patient Id | J3: Total Average of Patient Satisfaction Score | K3: Total Average of Patient Wait time | O3: 1 | P3: 336
B4: Row Labels | C4: Count of Patient Id | D4: Average of Patient Satisfaction Score | E4: Average of Patient Wait time | F4: Count of Patient Id | G4: Average of Patient Satisfaction Score | H4: Average of Patient Wait time | O4: 2 | P4: 293
B5: 1 | C5: 157 | D5: 4.9230769 | E5: 35.853503 | F5: 179 | G5: 5.1489362 | H5: 35.513966 | I5: 336 | J5: 5.0465116 | K5: 35.672619 | O5: 3 | P5: 316
B6: 2 | C6: 144 | D6: 4.7674419 | E6: 33.708333 | F6: 149 | G6: 5.0243902 | H6: 35.248322 | I6: 293 | J6: 4.8928571 | K6: 34.491468 | O6: 4 | P6: 288
B7: 3 | C7: 160 | D7: 4.5625 | E7: 35.6375 | F7: 156 | G7: 4.9591837 | H7: 35.878205 | I7: 316 | J7: 4.8024691 | K7: 35.756329 | O7: 5 | P7: 299
B8: 4 | C8: 144 | D8: 5.0512821 | E8: 35.069444 | F8: 144 | G8: 4.7045455 | H8: 34.944444 | I8: 288 | J8: 4.8674699 | K8: 35.006944 | O8: 6 | P8: 257
B9: 5 | C9: 143 | D9: 4.225 | E9: 34.300699 | F9: 156 | G9: 4.875 | H9: 33.634615 | I9: 299 | J9: 4.5795455 | K9: 33.953177 | O9: 7 | P9: 285
B10: 6 | C10: 116 | D10: 5.0232558 | E10: 33.189655 | F10: 141 | G10: 4.5555556 | H10: 37.014184 | I10: 257 | J10: 4.8101266 | K10: 35.287938 | O10: 8 | P10: 314
B11: 7 | C11: 137 | D11: 4.3793103 | E11: 35.350365 | F11: 148 | G11: 5.6304348 | H11: 36.790541 | I11: 285 | J11: 5.1466667 | K11: 36.098246 | O11: 9 | P11: 296
B12: 8 | C12: 154 | D12: 4.7297297 | E12: 36.155844 | F12: 160 | G12: 4.7727273 | H12: 34.36875 | I12: 314 | J12: 4.7530864 | K12: 35.245223 | O12: 10 | P12: 304
B13: 9 | C13: 152 | D13: 5 | E13: 33.677632 | F13: 144 | G13: 4.7333333 | H13: 35.986111 | I13: 296 | J13: 4.85 | K13: 34.800676 | O13: 11 | P13: 302
B14: 10 | C14: 169 | D14: 4.8378378 | E14: 36.035503 | F14: 135 | G14: 4.6 | H14: 33.948148 | I14: 304 | J14: 4.7313433 | K14: 35.108553 | O14: 12 | P14: 323
B15: 11 | C15: 155 | D15: 5.5869565 | E15: 35.258065 | F15: 147 | G15: 4.7941176 | H15: 37 | I15: 302 | J15: 5.25 | K15: 36.10596 | O15: 13 | P15: 268
B16: 12 | C16: 161 | D16: 4.972973 | E16: 37.192547 | F16: 162 | G16: 4.275 | H16: 34.697531 | I16: 323 | J16: 4.6103896 | K16: 35.941176 | O16: 14 | P16: 288
... B33: 29 | C33: 150 | D33: 5.1136364 | E33: 34.88 | F33: 162 | G33: 4.372549 | H33: 35.820988 | I33: 312 | J33: 4.7157895 | K33: 35.36859 | O33: 31 | P33: 160
B34: 30 | C34: 146 | D34: 5.7560976 | E34: 33.767123 | F34: 142 | G34: 4.425 | H34: 34.971831 | I34: 288 | J34: 5.0987654 | K34: 34.361111 | O34: Grand Total | P34: 9216
B35: 31 | C35: 79 | D35: 6 | E35: 36.443038 | F35: 81 | G35: 5.8148148 | H35: 37.740741 | I35: 160 | J35: 5.8809524 | K35: 37.1
B36: Grand Total | C36: 4612 | D36: 5.0769231 | E36: 34.96791 | F36: 4604 | G36: 4.9102964 | H36: 35.552346 | I36: 9216 | J36: 4.992054 | K36: 35.259874
O37: Row Labels | P37: Count of Patient Id | S37: Department | T37: No. of Patients
O38: Cardiology | P38: 248 | S38: Cardiology | T38: =GETPIVOTDATA("Patient Id",$O$37,"Department Referral",O38) -> 248
O39: Gastroenterology | P39: 178 | S39: Gastroenterology | T39: =GETPIVOTDATA("Patient Id",$O$37,"Department Referral",O39) -> 178
O40: General Practice | P40: 1840 | S40: General Practice | T40: =GETPIVOTDATA("Patient Id",$O$37,"Department Referral",O40) -> 1840
O41: Neurology | P41: 193 | S41: Neurology | T41: =GETPIVOTDATA("Patient Id",$O$37,"Department Referral",O41) -> 193
C42: Row Labels | D42: Count of Patient Id | O42: No Department Assigned | P42: 5400 | S42: No Department Assigned | T42: =GETPIVOTDATA("Patient Id",$O$37,"Department Referral",O42) -> 5400
C43: Much higher(>45) | D43: 2750 | F43: Row Labels | G43: Count of Patient Id | I43: Row Labels | J43: Count of Patient Id | O43: Orthopedics | P43: 995 | S43: Orthopedics | T43: =GETPIVOTDATA("Patient Id",$O$37,"Department Referral",O43) -> 995
C44: Within Target(<30) | D44: 3749 | F44: Female | G44: 4487 | I44: 0-5 | J44: 464 | O44: Physiotherapy | P44: 276 | S44: Physiotherapy | T44: =GETPIVOTDATA("Patient Id",$O$37,"Department Referral",O44) -> 276
C45: Slightly Above(<=45) | D45: 2717 | F45: Male | G45: 4729 | I45: 15-29 | J45: 1801 | O45: Renal | P45: 86 | S45: Renal | T45: =GETPIVOTDATA("Patient Id",$O$37,"Department Referral",O45) -> 86
C46: Grand Total | D46: 9216 | F46: Grand Total | G46: 9216 | I46: 30-45 | J46: 1755 | O46: Grand Total | P46: 9216
I47: 45-59 | J47: 1731
I48: 5-14 | J48: 1158
I49: 60-69 | J49: 1154
I50: 70-79 | J50: 1153
I51: Grand Total | J51: 9216

Sheet Wait Time Analysis
D2: Wait Time Analysis
C5: Wait Time Target | E5: Within Target | I5: Above Target
C7: 30 Mins | E7: =GETPIVOTDATA("Count of Patient Id",$B$18,"Wait Time slot","Within Target(<30)")/GETPIVOTDATA("Count of Patient Id",$B$18) -> 0.40679253 | I7: =(GETPIVOTDATA("Patient Id",$B$18,"Wait Time slot","Slightly Above(<=45)")+GETPIVOTDATA("Patient Id",$B$18,"Wait Time slot","Much higher(>45) "))/GETPIVOTDATA("Patient Id",$B$18) -> 0.59320747
B18: Row Labels | C18: Count of Patient Id
B19: Much higher(>45) | C19: 2750
B20: Within Target(<30) | C20: 3749
B21: Slightly Above(<=45) | C21: 2717
B22: Grand Total | C22: 9216

Sheet Monthly Report
G2: Monthly Report
D5: Total Patients | G5: Start(1-10) | J5: Middle(11-20) | M5: End(21-30)
D7: =GETPIVOTDATA("Patient Id",$C$12) -> 9216 | G7: =GETPIVOTDATA("Patient Id",$C$29,"Monthly Period","Start(1-10)")/GETPIVOTDATA("Patient Id",$C$29) -> 0.32421875 | J7: =GETPIVOTDATA("Patient Id",$C$29,"Monthly Period","Middle(11-20)")/GETPIVOTDATA("Patient Id",$C$29) -> 0.32834201 | M7: =GETPIVOTDATA("Patient Id",$C$29,"Monthly Period","End(21-30)")/GETPIVOTDATA("Patient Id",$C$29) -> 0.34743924
C12: Count of Patient Id | D12: Column Labels
C13: Row Labels | D13: Admitted | E13: Not Admitted | F13: Grand Total
C14: Jan | D14: 269 | E14: 244 | F14: 513
C15: Feb | D15: 224 | E15: 207 | F15: 431
C16: Mar | D16: 253 | E16: 253 | F16: 506
C17: Apr | D17: 454 | E17: 494 | F17: 948
C18: May | D18: 495 | E18: 504 | F18: 999
C19: Jun | D19: 487 | E19: 504 | F19: 991
C20: Jul | D20: 502 | E20: 450 | F20: 952
C21: Aug | D21: 476 | E21: 548 | F21: 1024
C22: Sep | D22: 485 | E22: 450 | F22: 935
C23: Oct | D23: 486 | E23: 478 | F23: 964
C24: Nov | D24: 231 | E24: 233 | F24: 464
C25: Dec | D25: 250 | E25: 239 | F25: 489
C26: Grand Total | D26: 4612 | E26: 4604 | F26: 9216
C29: Row Labels | D29: Count of Patient Id
C30: Start(1-10) | D30: 2988
C31: Middle(11-20) | D31: 3026
C32: End(21-30) | D32: 3202
C33: Grand Total | D33: 9216

Sheet Weekly Report
G2: Weekly Report
C5: Total Patients | H5: Highest Patient Day | M5: Lowest Patient Day
C7: =GETPIVOTDATA("Patient Id",$B$14) -> 9216 | I7: =INDEX(B15:B21,MATCH(MAX(C15:C21),C15:C21,0)) -> Saturday | M7: =INDEX(B15:B21,MATCH(MIN(C15:C21),C15:C21,0)) -> Wednesday
H8: =MAX(B15:C21) -> 1377 | M8: =MIN(B15:C21) -> 1260
B14: Row Labels | C14: Count of Patient Id
B15: Sunday | C15: 1318
B16: Monday | C16: 1314
B17: Tuesday | C17: 1305
B18: Wednesday | C18: 1260
B19: Thursday | C19: 1332
B20: Friday | C20: 1310
B21: Saturday | C21: 1377
B22: Grand Total | C22: 9216
B27: Row Labels | C27: Count of Patient Id
B28: Week 1 | C28: 2074
B29: Week 2 | C29: 2095
B30: Week 3 | C30: 2164
B31: Week 4 | C31: 2883
B32: Grand Total | C32: 9216

Sheet Daily Report
H2: Daily Report
B6: Count of Patient Id | C6: Column Labels | G6: Total Patients | J6: Admitted | M6: Not Admitted | P6: AVG Daily Patients
B7: Row Labels | C7: Admitted | D7: Not Admitted | E7: Grand Total
B8: 1 | C8: 157 | D8: 179 | E8: 336 | G8: =GETPIVOTDATA("Patient Id",$B$6) -> 9216 | J8: =GETPIVOTDATA("Patient Id",$B$6,"Patient Admission Flag","Admitted") -> 4612 | M8: =GETPIVOTDATA("Patient Id",$B$6,"Patient Admission Flag","Not Admitted") -> 4604 | P8: =(GETPIVOTDATA("Patient Id",$B$6)/COUNT(B8:B38)) -> 297.29032
B9: 2 | C9: 144 | D9: 149 | E9: 293
B10: 3 | C10: 160 | D10: 156 | E10: 316
B11: 4 | C11: 144 | D11: 144 | E11: 288
B12: 5 | C12: 143 | D12: 156 | E12: 299
B13: 6 | C13: 116 | D13: 141 | E13: 257
B14: 7 | C14: 137 | D14: 148 | E14: 285
B15: 8 | C15: 154 | D15: 160 | E15: 314
B16: 9 | C16: 152 | D16: 144 | E16: 296
B17: 10 | C17: 169 | D17: 135 | E17: 304
B18: 11 | C18: 155 | D18: 147 | E18: 302
B19: 12 | C19: 161 | D19: 162 | E19: 323
B20: 13 | C20: 158 | D20: 110 | E20: 268
... B38: 31 | C38: 79 | D38: 81 | E38: 160
B39: Grand Total | C39: 4612 | D39: 4604 | E39: 9216
B42: Row Labels | C42: Count of Patient Id
B43: 12AM - 6AM | C43: 2316
B44: 12PM - 6PM | C44: 2275
B45: 6AM - 12PM | C45: 2316
B46: 6PM - 12AM | C46: 2309
B47: Grand Total | C47: 9216

Sheet Sheet4
F2: Using Data Validation to see the Hospital Performance by months and years
C4: Jan | F4: Total Patients | G4: =COUNTIFS(Hospital_Emergency_Room_Data[[#All],[Month]],Sheet4!G7,Hospital_Emergency_Room_Data[[#All],[Year]],Sheet4!G8) -> 471
C5: Feb | F5: Admitted | G5: =COUNTIFS(Hospital_Emergency_Room_Data[[#All],[Month]],Sheet4!G7,Hospital_Emergency_Room_Data[[#All],[Year]],Sheet4!G8,Hospital_Emergency_Room_Data[[#All],[Patient Admission Flag]],"Admitted") -> 247
C6: Mar | F6: Not Admitted | G6: =COUNTIFS(Hospital_Emergency_Room_Data[[#All],[Month]],Sheet4!G7,Hospital_Emergency_Room_Data[[#All],[Year]],Sheet4!G8,Hospital_Emergency_Room_Data[[#All],[Patient Admission Flag]],"Not Admitted") -> 224
C7: Apr | F7: Month | G7: Oct
C8: May | F8: Year | G8: 2024
C9: Jun
C10: Jul
C11: Aug | G11: Data Validation + Vlookup,Xlookup
C12: Sep
C13: Oct | F13: Retrieving the departments name using patients ID
C14: Nov
C15: Dec | G15: Patients ID | H15: Department
G16: 408166050 | H16: =VLOOKUP(G16,Hospital_Emergency_Room_Data[#All],12,TRUE) -> Orthopedics
F18: Retrieve Patient wait time using patient's name
G20: Patient name | H20: Wait time
G21: Y. Gionettitti | H21: {=_xlfn.XLOOKUP(G21,Hospital_Emergency_Room_Data[[#All],[Full Name]],Hospital_Emergency_Room_Data[[#All],[Patient Wait time]],0,0)} -> 10
